{
"meta":{"test_sets":[],"test_metrics":[],"learn_metrics":[{"best_value":"Min","name":"RMSE"}],"launch_mode":"Train","parameters":"","iteration_count":1000,"learn_sets":["learn"],"name":"experiment"},
"iterations":[
{"learn":[8982.170456],"iteration":0,"passed_time":0.006012232989,"remaining_time":6.006220756},
{"learn":[8862.247091],"iteration":1,"passed_time":0.01099738961,"remaining_time":5.487697413},
{"learn":[8718.811842],"iteration":2,"passed_time":0.01550567823,"remaining_time":5.153053732},
{"learn":[8590.366873],"iteration":3,"passed_time":0.01772168293,"remaining_time":4.41269905},
{"learn":[8457.456017],"iteration":4,"passed_time":0.01946986439,"remaining_time":3.874503013},
{"learn":[8297.015969],"iteration":5,"passed_time":0.02094950406,"remaining_time":3.470634505},
{"learn":[8157.479036],"iteration":6,"passed_time":0.02273358733,"remaining_time":3.224921746},
{"learn":[8042.987964],"iteration":7,"passed_time":0.02680747279,"remaining_time":3.324126627},
{"learn":[7944.665857],"iteration":8,"passed_time":0.03026730167,"remaining_time":3.332766218},
{"learn":[7825.093356],"iteration":9,"passed_time":0.03348132351,"remaining_time":3.314651027},
{"learn":[7680.60966],"iteration":10,"passed_time":0.03630720268,"remaining_time":3.264347586},
{"learn":[7561.02633],"iteration":11,"passed_time":0.03820287826,"remaining_time":3.14537031},
{"learn":[7445.98082],"iteration":12,"passed_time":0.04324175809,"remaining_time":3.283047326},
{"learn":[7319.001757],"iteration":13,"passed_time":0.04515176433,"remaining_time":3.179974259},
{"learn":[7219.836128],"iteration":14,"passed_time":0.04773877203,"remaining_time":3.13484603},
{"learn":[7106.449653],"iteration":15,"passed_time":0.05465997076,"remaining_time":3.361588202},
{"learn":[6988.920146],"iteration":16,"passed_time":0.05668202097,"remaining_time":3.277554507},
{"learn":[6899.372181],"iteration":17,"passed_time":0.0729776546,"remaining_time":3.98133649},
{"learn":[6812.903662],"iteration":18,"passed_time":0.07485168595,"remaining_time":3.864710733},
{"learn":[6694.428408],"iteration":19,"passed_time":0.07613715798,"remaining_time":3.730720741},
{"learn":[6585.048779],"iteration":20,"passed_time":0.07769616425,"remaining_time":3.622121181},
{"learn":[6484.003803],"iteration":21,"passed_time":0.09006726211,"remaining_time":4.003899197},
{"learn":[6382.662543],"iteration":22,"passed_time":0.09220531861,"remaining_time":3.916721577},
{"learn":[6287.657585],"iteration":23,"passed_time":0.09390808191,"remaining_time":3.818928664},
{"learn":[6194.412475],"iteration":24,"passed_time":0.09543086028,"remaining_time":3.721803551},
{"learn":[6072.290078],"iteration":25,"passed_time":0.1006498222,"remaining_time":3.770497187},
{"learn":[5965.845862],"iteration":26,"passed_time":0.1047536268,"remaining_time":3.775010329},
{"learn":[5852.019452],"iteration":27,"passed_time":0.1066086134,"remaining_time":3.700841866},
{"learn":[5755.406791],"iteration":28,"passed_time":0.1084274718,"remaining_time":3.630450865},
{"learn":[5653.001955],"iteration":29,"passed_time":0.1112063212,"remaining_time":3.595671051},
{"learn":[5561.389478],"iteration":30,"passed_time":0.1129269602,"remaining_time":3.529878207},
{"learn":[5467.125858],"iteration":31,"passed_time":0.1144909191,"remaining_time":3.463350301},
{"learn":[5383.147218],"iteration":32,"passed_time":0.1170965857,"remaining_time":3.431284798},
{"learn":[5319.625301],"iteration":33,"passed_time":0.1187738928,"remaining_time":3.374575894},
{"learn":[5226.963421],"iteration":34,"passed_time":0.1200811147,"remaining_time":3.310807876},
{"learn":[5150.190905],"iteration":35,"passed_time":0.1223449915,"remaining_time":3.276126995},
{"learn":[5066.928708],"iteration":36,"passed_time":0.1253174186,"remaining_time":3.261639841},
{"learn":[4994.744723],"iteration":37,"passed_time":0.127123753,"remaining_time":3.218238167},
{"learn":[4922.523458],"iteration":38,"passed_time":0.1300865961,"remaining_time":3.20546715},
{"learn":[4838.308599],"iteration":39,"passed_time":0.1327160644,"remaining_time":3.185185545},
{"learn":[4765.319512],"iteration":40,"passed_time":0.1357040944,"remaining_time":3.174151867},
{"learn":[4691.291905],"iteration":41,"passed_time":0.1374562466,"remaining_time":3.135311531},
{"learn":[4619.796927],"iteration":42,"passed_time":0.1397732537,"remaining_time":3.11076753},
{"learn":[4548.739131],"iteration":43,"passed_time":0.1435811945,"remaining_time":3.119627771},
{"learn":[4487.073178],"iteration":44,"passed_time":0.1464447761,"remaining_time":3.107883581},
{"learn":[4406.565439],"iteration":45,"passed_time":0.1484718598,"remaining_time":3.079177266},
{"learn":[4336.805152],"iteration":46,"passed_time":0.1507566876,"remaining_time":3.056832411},
{"learn":[4265.826418],"iteration":47,"passed_time":0.1536589487,"remaining_time":3.047569149},
{"learn":[4186.689863],"iteration":48,"passed_time":0.1568407104,"remaining_time":3.043990114},
{"learn":[4139.495691],"iteration":49,"passed_time":0.1590263274,"remaining_time":3.021500221},
{"learn":[4079.887754],"iteration":50,"passed_time":0.1635608488,"remaining_time":3.043514617},
{"learn":[4027.629212],"iteration":51,"passed_time":0.1664682985,"remaining_time":3.034845134},
{"learn":[3964.392486],"iteration":52,"passed_time":0.1704161656,"remaining_time":3.044983185},
{"learn":[3890.033077],"iteration":53,"passed_time":0.173191174,"remaining_time":3.03405279},
{"learn":[3842.706603],"iteration":54,"passed_time":0.1844204192,"remaining_time":3.168678112},
{"learn":[3780.425009],"iteration":55,"passed_time":0.1890976832,"remaining_time":3.187646659},
{"learn":[3726.644404],"iteration":56,"passed_time":0.1911408058,"remaining_time":3.162206664},
{"learn":[3664.700712],"iteration":57,"passed_time":0.1936735016,"remaining_time":3.145524801},
{"learn":[3599.930591],"iteration":58,"passed_time":0.1967141679,"remaining_time":3.137424271},
{"learn":[3550.012476],"iteration":59,"passed_time":0.1995682259,"remaining_time":3.126568873},
{"learn":[3502.223456],"iteration":60,"passed_time":0.2031739132,"remaining_time":3.127545975},
{"learn":[3456.110997],"iteration":61,"passed_time":0.2050505198,"remaining_time":3.102215929},
{"learn":[3400.300217],"iteration":62,"passed_time":0.2068165565,"remaining_time":3.075985928},
{"learn":[3339.371322],"iteration":63,"passed_time":0.2101270091,"remaining_time":3.073107508},
{"learn":[3293.725288],"iteration":64,"passed_time":0.2118179501,"remaining_time":3.046919743},
{"learn":[3249.046414],"iteration":65,"passed_time":0.2151358606,"remaining_time":3.04449839},
{"learn":[3209.696494],"iteration":66,"passed_time":0.2176450849,"remaining_time":3.030789018},
{"learn":[3165.914943],"iteration":67,"passed_time":0.2193509374,"remaining_time":3.006398142},
{"learn":[3119.797692],"iteration":68,"passed_time":0.2258120413,"remaining_time":3.046826238},
{"learn":[3077.785495],"iteration":69,"passed_time":0.228601102,"remaining_time":3.037128927},
{"learn":[3033.570396],"iteration":70,"passed_time":0.2300526757,"remaining_time":3.010125856},
{"learn":[2988.545142],"iteration":71,"passed_time":0.2320674492,"remaining_time":2.991091568},
{"learn":[2947.913036],"iteration":72,"passed_time":0.2357923515,"remaining_time":2.994239861},
{"learn":[2897.630838],"iteration":73,"passed_time":0.2390500893,"remaining_time":2.991356523},
{"learn":[2858.068215],"iteration":74,"passed_time":0.2448251633,"remaining_time":3.019510347},
{"learn":[2810.630727],"iteration":75,"passed_time":0.2495187137,"remaining_time":3.033622256},
{"learn":[2774.112694],"iteration":76,"passed_time":0.2518099759,"remaining_time":3.018449451},
{"learn":[2738.724451],"iteration":77,"passed_time":0.2543252246,"remaining_time":3.006254579},
{"learn":[2701.764177],"iteration":78,"passed_time":0.2563743083,"remaining_time":2.9888701},
{"learn":[2665.544293],"iteration":79,"passed_time":0.2641371863,"remaining_time":3.037577643},
{"learn":[2625.78161],"iteration":80,"passed_time":0.2652744209,"remaining_time":3.00971843},
{"learn":[2590.416148],"iteration":81,"passed_time":0.2697447221,"remaining_time":3.019825059},
{"learn":[2558.309468],"iteration":82,"passed_time":0.2711375983,"remaining_time":2.995580453},
{"learn":[2523.780487],"iteration":83,"passed_time":0.272709233,"remaining_time":2.973829255},
{"learn":[2491.39717],"iteration":84,"passed_time":0.274168005,"remaining_time":2.951337936},
{"learn":[2460.442993],"iteration":85,"passed_time":0.2841434628,"remaining_time":3.019850291},
{"learn":[2425.857644],"iteration":86,"passed_time":0.2929611873,"remaining_time":3.074408782},
{"learn":[2395.025329],"iteration":87,"passed_time":0.2962988889,"remaining_time":3.070733939},
{"learn":[2370.89766],"iteration":88,"passed_time":0.3076079372,"remaining_time":3.148661021},
{"learn":[2340.643536],"iteration":89,"passed_time":0.3104618896,"remaining_time":3.139114662},
{"learn":[2304.923667],"iteration":90,"passed_time":0.3125987566,"remaining_time":3.122552414},
{"learn":[2271.296723],"iteration":91,"passed_time":0.3187912577,"remaining_time":3.146331108},
{"learn":[2246.337265],"iteration":92,"passed_time":0.3235277686,"remaining_time":3.155265443},
{"learn":[2219.59258],"iteration":93,"passed_time":0.3275795981,"remaining_time":3.157309743},
{"learn":[2193.166273],"iteration":94,"passed_time":0.3298727376,"remaining_time":3.142471869},
{"learn":[2168.908664],"iteration":95,"passed_time":0.3325791252,"remaining_time":3.131786762},
{"learn":[2143.056793],"iteration":96,"passed_time":0.341257779,"remaining_time":3.176863654},
{"learn":[2119.153082],"iteration":97,"passed_time":0.3443245168,"remaining_time":3.169190961},
{"learn":[2091.846939],"iteration":98,"passed_time":0.356019057,"remaining_time":3.240133034},
{"learn":[2071.500691],"iteration":99,"passed_time":0.3605939558,"remaining_time":3.245345602},
{"learn":[2048.623643],"iteration":100,"passed_time":0.3682333165,"remaining_time":3.277641104},
{"learn":[2025.902693],"iteration":101,"passed_time":0.3701847623,"remaining_time":3.259077613},
{"learn":[1998.80459],"iteration":102,"passed_time":0.3748987269,"remaining_time":3.264894738},
{"learn":[1972.0803],"iteration":103,"passed_time":0.3772976415,"remaining_time":3.250564296},
{"learn":[1948.840827],"iteration":104,"passed_time":0.3797710105,"remaining_time":3.237095756},
{"learn":[1923.133558],"iteration":105,"passed_time":0.3822776173,"remaining_time":3.224114998},
{"learn":[1902.760571],"iteration":106,"passed_time":0.385971458,"remaining_time":3.22123843},
{"learn":[1881.327778],"iteration":107,"passed_time":0.3879306014,"remaining_time":3.204019411},
{"learn":[1859.946232],"iteration":108,"passed_time":0.3895246043,"remaining_time":3.184095619},
{"learn":[1837.444093],"iteration":109,"passed_time":0.3921785645,"remaining_time":3.173081113},
{"learn":[1815.527753],"iteration":110,"passed_time":0.3943142757,"remaining_time":3.158066587},
{"learn":[1792.280503],"iteration":111,"passed_time":0.396318225,"remaining_time":3.142237355},
{"learn":[1770.198326],"iteration":112,"passed_time":0.3985230395,"remaining_time":3.128229523},
{"learn":[1750.982295],"iteration":113,"passed_time":0.4006121141,"remaining_time":3.113529238},
{"learn":[1731.549346],"iteration":114,"passed_time":0.4027566581,"remaining_time":3.099475152},
{"learn":[1712.174066],"iteration":115,"passed_time":0.4050966928,"remaining_time":3.087116176},
{"learn":[1695.835825],"iteration":116,"passed_time":0.4069679043,"remaining_time":3.071390252},
{"learn":[1680.083585],"iteration":117,"passed_time":0.4094197311,"remaining_time":3.060239007},
{"learn":[1663.335183],"iteration":118,"passed_time":0.4139944553,"remaining_time":3.064950548},
{"learn":[1644.966761],"iteration":119,"passed_time":0.4174968741,"remaining_time":3.061643743},
{"learn":[1625.490602],"iteration":120,"passed_time":0.4212032146,"remaining_time":3.059815088},
{"learn":[1610.281234],"iteration":121,"passed_time":0.4297757124,"remaining_time":3.092976028},
{"learn":[1594.478833],"iteration":122,"passed_time":0.4320074184,"remaining_time":3.080248016},
{"learn":[1574.33956],"iteration":123,"passed_time":0.4344678426,"remaining_time":3.069305081},
{"learn":[1555.741178],"iteration":124,"passed_time":0.4423765705,"remaining_time":3.096635994},
{"learn":[1544.118616],"iteration":125,"passed_time":0.4457080617,"remaining_time":3.091657508},
{"learn":[1527.938417],"iteration":126,"passed_time":0.4652551697,"remaining_time":3.198171363},
{"learn":[1505.772939],"iteration":127,"passed_time":0.4682990097,"remaining_time":3.190287004},
{"learn":[1491.517432],"iteration":128,"passed_time":0.4703484067,"remaining_time":3.175763273},
{"learn":[1474.48357],"iteration":129,"passed_time":0.4725573201,"remaining_time":3.162498988},
{"learn":[1456.381034],"iteration":130,"passed_time":0.4809415369,"remaining_time":3.190367905},
{"learn":[1442.164227],"iteration":131,"passed_time":0.4855061216,"remaining_time":3.192570557},
{"learn":[1426.214916],"iteration":132,"passed_time":0.4870001916,"remaining_time":3.174655384},
{"learn":[1412.772533],"iteration":133,"passed_time":0.4900347085,"remaining_time":3.166940728},
{"learn":[1397.39643],"iteration":134,"passed_time":0.4924176283,"remaining_time":3.155120359},
{"learn":[1383.17358],"iteration":135,"passed_time":0.4969407228,"remaining_time":3.15703518},
{"learn":[1365.130744],"iteration":136,"passed_time":0.5017474288,"remaining_time":3.160642563},
{"learn":[1350.894522],"iteration":137,"passed_time":0.5051253894,"remaining_time":3.15520352},
{"learn":[1335.309735],"iteration":138,"passed_time":0.507155101,"remaining_time":3.141442748},
{"learn":[1321.200413],"iteration":139,"passed_time":0.5123512473,"remaining_time":3.147300519},
{"learn":[1306.372982],"iteration":140,"passed_time":0.5214392762,"remaining_time":3.176711619},
{"learn":[1292.512231],"iteration":141,"passed_time":0.5262048035,"remaining_time":3.179462827},
{"learn":[1278.68894],"iteration":142,"passed_time":0.5386761116,"remaining_time":3.228289703},
{"learn":[1265.324496],"iteration":143,"passed_time":0.5408484643,"remaining_time":3.215043649},
{"learn":[1251.069915],"iteration":144,"passed_time":0.5467385784,"remaining_time":3.223872307},
{"learn":[1239.126216],"iteration":145,"passed_time":0.5575417442,"remaining_time":3.261237326},
{"learn":[1227.214279],"iteration":146,"passed_time":0.5597107168,"remaining_time":3.24784518},
{"learn":[1215.600249],"iteration":147,"passed_time":0.5611656345,"remaining_time":3.230494058},
{"learn":[1203.620652],"iteration":148,"passed_time":0.5625545683,"remaining_time":3.212979447},
{"learn":[1192.018268],"iteration":149,"passed_time":0.5639946041,"remaining_time":3.195969423},
{"learn":[1181.647601],"iteration":150,"passed_time":0.5678564854,"remaining_time":3.192782491},
{"learn":[1169.101686],"iteration":151,"passed_time":0.5772556573,"remaining_time":3.22047893},
{"learn":[1158.336013],"iteration":152,"passed_time":0.578907132,"remaining_time":3.204799613},
{"learn":[1149.386361],"iteration":153,"passed_time":0.5803608095,"remaining_time":3.188215876},
{"learn":[1137.033826],"iteration":154,"passed_time":0.5818394414,"remaining_time":3.171963406},
{"learn":[1126.717322],"iteration":155,"passed_time":0.5927445763,"remaining_time":3.206900144},
{"learn":[1113.446481],"iteration":156,"passed_time":0.5959683361,"remaining_time":3.200008327},
{"learn":[1103.413301],"iteration":157,"passed_time":0.5973582825,"remaining_time":3.183390341},
{"learn":[1092.088783],"iteration":158,"passed_time":0.5986751288,"remaining_time":3.166577254},
{"learn":[1083.576505],"iteration":159,"passed_time":0.6108982664,"remaining_time":3.207215899},
{"learn":[1072.551119],"iteration":160,"passed_time":0.6151761504,"remaining_time":3.205793728},
{"learn":[1060.771878],"iteration":161,"passed_time":0.6173033948,"remaining_time":3.193211388},
{"learn":[1051.168345],"iteration":162,"passed_time":0.6329667423,"remaining_time":3.250264805},
{"learn":[1039.783771],"iteration":163,"passed_time":0.6352072394,"remaining_time":3.238007635},
{"learn":[1031.133605],"iteration":164,"passed_time":0.6456244756,"remaining_time":3.267251134},
{"learn":[1023.257762],"iteration":165,"passed_time":0.6524453652,"remaining_time":3.277948401},
{"learn":[1014.885459],"iteration":166,"passed_time":0.6545140176,"remaining_time":3.264731597},
{"learn":[1005.649822],"iteration":167,"passed_time":0.6558943028,"remaining_time":3.248238452},
{"learn":[993.9952831],"iteration":168,"passed_time":0.6635340114,"remaining_time":3.262702742},
{"learn":[986.5929733],"iteration":169,"passed_time":0.667588869,"remaining_time":3.259404478},
{"learn":[978.3689952],"iteration":170,"passed_time":0.6708156847,"remaining_time":3.252083056},
{"learn":[969.1407859],"iteration":171,"passed_time":0.6723474976,"remaining_time":3.236649581},
{"learn":[959.8239161],"iteration":172,"passed_time":0.6775733347,"remaining_time":3.239035537},
{"learn":[951.3717826],"iteration":173,"passed_time":0.6847895531,"remaining_time":3.250782591},
{"learn":[942.561811],"iteration":174,"passed_time":0.6868838327,"remaining_time":3.23816664},
{"learn":[933.3375203],"iteration":175,"passed_time":0.6889922376,"remaining_time":3.225736385},
{"learn":[923.3953982],"iteration":176,"passed_time":0.6915753192,"remaining_time":3.215629874},
{"learn":[914.4075637],"iteration":177,"passed_time":0.6944807189,"remaining_time":3.207096354},
{"learn":[906.9696897],"iteration":178,"passed_time":0.6980750947,"remaining_time":3.201785769},
{"learn":[899.0372573],"iteration":179,"passed_time":0.7007766021,"remaining_time":3.192426743},
{"learn":[891.3668624],"iteration":180,"passed_time":0.7031537263,"remaining_time":3.181673491},
{"learn":[882.4619747],"iteration":181,"passed_time":0.7066918898,"remaining_time":3.176230582},
{"learn":[874.8726428],"iteration":182,"passed_time":0.7097819481,"remaining_time":3.168807932},
{"learn":[867.5713121],"iteration":183,"passed_time":0.7121320112,"remaining_time":3.158150658},
{"learn":[859.7880595],"iteration":184,"passed_time":0.7136854972,"remaining_time":3.144073947},
{"learn":[852.8012072],"iteration":185,"passed_time":0.7152142161,"remaining_time":3.130023505},
{"learn":[845.3872135],"iteration":186,"passed_time":0.7165490952,"remaining_time":3.115264248},
{"learn":[837.9836577],"iteration":187,"passed_time":0.722385215,"remaining_time":3.120089333},
{"learn":[829.595456],"iteration":188,"passed_time":0.7254505918,"remaining_time":3.112912328},
{"learn":[822.3432095],"iteration":189,"passed_time":0.7274236117,"remaining_time":3.101121713},
{"learn":[813.6890692],"iteration":190,"passed_time":0.7293538951,"remaining_time":3.089252886},
{"learn":[806.0821166],"iteration":191,"passed_time":0.7332564884,"remaining_time":3.085787722},
{"learn":[799.1958232],"iteration":192,"passed_time":0.736004862,"remaining_time":3.077491832},
{"learn":[790.0395729],"iteration":193,"passed_time":0.7410853353,"remaining_time":3.078942166},
{"learn":[783.1701707],"iteration":194,"passed_time":0.7429899029,"remaining_time":3.067214727},
{"learn":[775.6889179],"iteration":195,"passed_time":0.7472035172,"remaining_time":3.065059326},
{"learn":[768.425904],"iteration":196,"passed_time":0.7625757892,"remaining_time":3.108367303},
{"learn":[760.9805977],"iteration":197,"passed_time":0.7646261964,"remaining_time":3.09712227},
{"learn":[754.424794],"iteration":198,"passed_time":0.7678992757,"remaining_time":3.090891054},
{"learn":[748.176679],"iteration":199,"passed_time":0.7693400186,"remaining_time":3.077360074},
{"learn":[741.9452235],"iteration":200,"passed_time":0.7718601366,"remaining_time":3.068240045},
{"learn":[735.6711637],"iteration":201,"passed_time":0.7741514755,"remaining_time":3.058281572},
{"learn":[728.0983603],"iteration":202,"passed_time":0.7756171788,"remaining_time":3.045157101},
{"learn":[720.7079041],"iteration":203,"passed_time":0.7780308014,"remaining_time":3.035845676},
{"learn":[715.0033554],"iteration":204,"passed_time":0.7795714598,"remaining_time":3.023216149},
{"learn":[708.1795586],"iteration":205,"passed_time":0.7819155334,"remaining_time":3.01379094},
{"learn":[701.6117788],"iteration":206,"passed_time":0.7834032185,"remaining_time":3.001153393},
{"learn":[695.2960284],"iteration":207,"passed_time":0.7871217903,"remaining_time":2.997117586},
{"learn":[690.6198759],"iteration":208,"passed_time":0.7914512805,"remaining_time":2.995396951},
{"learn":[684.5867262],"iteration":209,"passed_time":0.7946332064,"remaining_time":2.989334443},
{"learn":[678.2601265],"iteration":210,"passed_time":0.7962389738,"remaining_time":2.977405452},
{"learn":[671.7537746],"iteration":211,"passed_time":0.8004305315,"remaining_time":2.975185183},
{"learn":[665.9206576],"iteration":212,"passed_time":0.8135993035,"remaining_time":3.006115736},
{"learn":[659.8220474],"iteration":213,"passed_time":0.8155229913,"remaining_time":2.995332108},
{"learn":[652.3466098],"iteration":214,"passed_time":0.8177619897,"remaining_time":2.985782149},
{"learn":[646.085602],"iteration":215,"passed_time":0.8319462851,"remaining_time":3.019656887},
{"learn":[640.2923054],"iteration":216,"passed_time":0.8341567666,"remaining_time":3.009883632},
{"learn":[634.1557924],"iteration":217,"passed_time":0.8404366181,"remaining_time":3.014777226},
{"learn":[628.941154],"iteration":218,"passed_time":0.8519240681,"remaining_time":3.03814017},
{"learn":[623.4619881],"iteration":219,"passed_time":0.854416404,"remaining_time":3.029294523},
{"learn":[619.0734987],"iteration":220,"passed_time":0.8563450426,"remaining_time":3.018519403},
{"learn":[612.4870905],"iteration":221,"passed_time":0.8617148704,"remaining_time":3.019883645},
{"learn":[607.5917211],"iteration":222,"passed_time":0.8725569572,"remaining_time":3.04025451},
{"learn":[601.7450138],"iteration":223,"passed_time":0.875396129,"remaining_time":3.032622304},
{"learn":[596.825414],"iteration":224,"passed_time":0.883298268,"remaining_time":3.042471812},
{"learn":[592.0328101],"iteration":225,"passed_time":0.8913592531,"remaining_time":3.052708239},
{"learn":[588.1981622],"iteration":226,"passed_time":0.8938093669,"remaining_time":3.043676831},
{"learn":[584.1997704],"iteration":227,"passed_time":0.9029617717,"remaining_time":3.057396876},
{"learn":[579.201692],"iteration":228,"passed_time":0.9051329965,"remaining_time":3.04741284},
{"learn":[575.4800178],"iteration":229,"passed_time":0.9093263301,"remaining_time":3.044266409},
{"learn":[570.9986547],"iteration":230,"passed_time":0.9149368735,"remaining_time":3.045828813},
{"learn":[566.3118191],"iteration":231,"passed_time":0.9211837246,"remaining_time":3.049435778},
{"learn":[560.6498624],"iteration":232,"passed_time":0.9233999394,"remaining_time":3.039689929},
{"learn":[555.9566937],"iteration":233,"passed_time":0.9252722746,"remaining_time":3.028882745},
{"learn":[551.3634442],"iteration":234,"passed_time":0.9295255974,"remaining_time":3.025902477},
{"learn":[545.5433646],"iteration":235,"passed_time":0.9343030727,"remaining_time":3.024608252},
{"learn":[541.1524881],"iteration":236,"passed_time":0.9408336446,"remaining_time":3.028928569},
{"learn":[536.5003826],"iteration":237,"passed_time":0.9429733858,"remaining_time":3.019099664},
{"learn":[531.2833542],"iteration":238,"passed_time":0.9503150863,"remaining_time":3.025898664},
{"learn":[526.8576468],"iteration":239,"passed_time":0.9620364353,"remaining_time":3.046448712},
{"learn":[522.3348241],"iteration":240,"passed_time":0.9840465203,"remaining_time":3.099134062},
{"learn":[517.5741902],"iteration":241,"passed_time":0.9889355161,"remaining_time":3.097574881},
{"learn":[512.4936724],"iteration":242,"passed_time":1.013659442,"remaining_time":3.157778592},
{"learn":[507.9825994],"iteration":243,"passed_time":1.015963639,"remaining_time":3.147821767},
{"learn":[503.0055488],"iteration":244,"passed_time":1.017744787,"remaining_time":3.136315567},
{"learn":[497.2477148],"iteration":245,"passed_time":1.030402229,"remaining_time":3.158224718},
{"learn":[493.1616691],"iteration":246,"passed_time":1.032707137,"remaining_time":3.148293416},
{"learn":[489.1367209],"iteration":247,"passed_time":1.046424017,"remaining_time":3.173027664},
{"learn":[483.5244479],"iteration":248,"passed_time":1.049266976,"remaining_time":3.164656622},
{"learn":[480.7539424],"iteration":249,"passed_time":1.065940528,"remaining_time":3.197821584},
{"learn":[476.580288],"iteration":250,"passed_time":1.067510368,"remaining_time":3.185518986},
{"learn":[472.1738136],"iteration":251,"passed_time":1.080453022,"remaining_time":3.207058971},
{"learn":[468.5783962],"iteration":252,"passed_time":1.082645589,"remaining_time":3.196585987},
{"learn":[464.9651151],"iteration":253,"passed_time":1.084388045,"remaining_time":3.184856228},
{"learn":[460.5332238],"iteration":254,"passed_time":1.095901729,"remaining_time":3.201752109},
{"learn":[456.2966461],"iteration":255,"passed_time":1.097850449,"remaining_time":3.190627869},
{"learn":[453.813257],"iteration":256,"passed_time":1.100050702,"remaining_time":3.180302224},
{"learn":[450.079827],"iteration":257,"passed_time":1.113152694,"remaining_time":3.201392632},
{"learn":[446.6960668],"iteration":258,"passed_time":1.115495209,"remaining_time":3.191436099},
{"learn":[443.2724175],"iteration":259,"passed_time":1.128196649,"remaining_time":3.21102123},
{"learn":[439.5951873],"iteration":260,"passed_time":1.13026506,"remaining_time":3.200252411},
{"learn":[434.9942068],"iteration":261,"passed_time":1.132319475,"remaining_time":3.189510584},
{"learn":[431.7656248],"iteration":262,"passed_time":1.143859348,"remaining_time":3.20541574},
{"learn":[428.9012736],"iteration":263,"passed_time":1.145319316,"remaining_time":3.193011425},
{"learn":[424.6259917],"iteration":264,"passed_time":1.146670089,"remaining_time":3.180386851},
{"learn":[420.6688632],"iteration":265,"passed_time":1.158413917,"remaining_time":3.19652562},
{"learn":[417.4425734],"iteration":266,"passed_time":1.160445529,"remaining_time":3.185792408},
{"learn":[414.1565764],"iteration":267,"passed_time":1.162687847,"remaining_time":3.17569964},
{"learn":[410.6655653],"iteration":268,"passed_time":1.176165384,"remaining_time":3.196196638},
{"learn":[407.1857467],"iteration":269,"passed_time":1.177855442,"remaining_time":3.184572122},
{"learn":[404.2851329],"iteration":270,"passed_time":1.189657108,"remaining_time":3.200221521},
{"learn":[401.2678304],"iteration":271,"passed_time":1.192052433,"remaining_time":3.190493277},
{"learn":[397.2006908],"iteration":272,"passed_time":1.194459262,"remaining_time":3.180849389},
{"learn":[394.0185455],"iteration":273,"passed_time":1.196063084,"remaining_time":3.169130653},
{"learn":[390.8887907],"iteration":274,"passed_time":1.197564144,"remaining_time":3.157214561},
{"learn":[387.8957039],"iteration":275,"passed_time":1.210502921,"remaining_time":3.175377227},
{"learn":[385.0138213],"iteration":276,"passed_time":1.212111608,"remaining_time":3.163742573},
{"learn":[381.4338942],"iteration":277,"passed_time":1.213597688,"remaining_time":3.151861622},
{"learn":[378.7621767],"iteration":278,"passed_time":1.226061968,"remaining_time":3.168425373},
{"learn":[376.7035875],"iteration":279,"passed_time":1.227464549,"remaining_time":3.156337412},
{"learn":[373.9907347],"iteration":280,"passed_time":1.228770408,"remaining_time":3.144078018},
{"learn":[372.4241177],"iteration":281,"passed_time":1.233653205,"remaining_time":3.141003551},
{"learn":[369.8083562],"iteration":282,"passed_time":1.242403263,"remaining_time":3.147714274},
{"learn":[366.1892936],"iteration":283,"passed_time":1.244862127,"remaining_time":3.138455221},
{"learn":[363.4876211],"iteration":284,"passed_time":1.246332702,"remaining_time":3.126764497},
{"learn":[360.942096],"iteration":285,"passed_time":1.261378486,"remaining_time":3.149035801},
{"learn":[357.222399],"iteration":286,"passed_time":1.263500783,"remaining_time":3.138940969},
{"learn":[355.3197421],"iteration":287,"passed_time":1.273097394,"remaining_time":3.14737967},
{"learn":[353.7397381],"iteration":288,"passed_time":1.29305162,"remaining_time":3.181175438},
{"learn":[351.203327],"iteration":289,"passed_time":1.295399703,"remaining_time":3.171495824},
{"learn":[349.403972],"iteration":290,"passed_time":1.309461075,"remaining_time":3.190405162},
{"learn":[347.6351333],"iteration":291,"passed_time":1.311779103,"remaining_time":3.180615084},
{"learn":[346.0282626],"iteration":292,"passed_time":1.314505104,"remaining_time":3.171860438},
{"learn":[344.2629309],"iteration":293,"passed_time":1.328439371,"remaining_time":3.19006189},
{"learn":[342.3926647],"iteration":294,"passed_time":1.330116412,"remaining_time":3.178752781},
{"learn":[340.7213347],"iteration":295,"passed_time":1.342897015,"remaining_time":3.193917226},
{"learn":[339.0785172],"iteration":296,"passed_time":1.344771286,"remaining_time":3.183078161},
{"learn":[337.4637566],"iteration":297,"passed_time":1.347185971,"remaining_time":3.17357232},
{"learn":[335.806388],"iteration":298,"passed_time":1.349339856,"remaining_time":3.163502471},
{"learn":[334.1221069],"iteration":299,"passed_time":1.363872038,"remaining_time":3.18236809},
{"learn":[332.3182603],"iteration":300,"passed_time":1.366239475,"remaining_time":3.172762103},
{"learn":[329.3525383],"iteration":301,"passed_time":1.377892806,"remaining_time":3.184666153},
{"learn":[327.8398362],"iteration":302,"passed_time":1.381014837,"remaining_time":3.176789905},
{"learn":[325.4955339],"iteration":303,"passed_time":1.383553458,"remaining_time":3.167609232},
{"learn":[324.0095346],"iteration":304,"passed_time":1.385457219,"remaining_time":3.157025465},
{"learn":[321.1928825],"iteration":305,"passed_time":1.387654152,"remaining_time":3.147163338},
{"learn":[319.9634754],"iteration":306,"passed_time":1.391103713,"remaining_time":3.14017874},
{"learn":[318.4634158],"iteration":307,"passed_time":1.396086216,"remaining_time":3.136661237},
{"learn":[315.96913],"iteration":308,"passed_time":1.397873401,"remaining_time":3.125988737},
{"learn":[314.772712],"iteration":309,"passed_time":1.399671103,"remaining_time":3.115396972},
{"learn":[311.6681922],"iteration":310,"passed_time":1.402310852,"remaining_time":3.106727257},
{"learn":[310.3050307],"iteration":311,"passed_time":1.404203934,"remaining_time":3.096449702},
{"learn":[308.9667553],"iteration":312,"passed_time":1.406038983,"remaining_time":3.086098342},
{"learn":[307.68445],"iteration":313,"passed_time":1.409171804,"remaining_time":3.078636488},
{"learn":[306.3116581],"iteration":314,"passed_time":1.41121262,"remaining_time":3.068827444},
{"learn":[303.3229839],"iteration":315,"passed_time":1.413878618,"remaining_time":3.060420807},
{"learn":[299.9251101],"iteration":316,"passed_time":1.415823688,"remaining_time":3.050497095},
{"learn":[298.6692401],"iteration":317,"passed_time":1.417641248,"remaining_time":3.040350097},
{"learn":[297.367333],"iteration":318,"passed_time":1.422600105,"remaining_time":3.036961352},
{"learn":[296.2826908],"iteration":319,"passed_time":1.427020906,"remaining_time":3.032419426},
{"learn":[293.0187489],"iteration":320,"passed_time":1.428981009,"remaining_time":3.022673225},
{"learn":[291.0854889],"iteration":321,"passed_time":1.435552967,"remaining_time":3.022686062},
{"learn":[289.855133],"iteration":322,"passed_time":1.443599795,"remaining_time":3.025749415},
{"learn":[288.8825364],"iteration":323,"passed_time":1.445943735,"remaining_time":3.01684557},
{"learn":[288.2092815],"iteration":324,"passed_time":1.456630007,"remaining_time":3.025308475},
{"learn":[287.2548855],"iteration":325,"passed_time":1.466084096,"remaining_time":3.031106383},
{"learn":[284.5864911],"iteration":326,"passed_time":1.469578964,"remaining_time":3.024546308},
{"learn":[283.5797594],"iteration":327,"passed_time":1.472075188,"remaining_time":3.015958922},
{"learn":[282.5892571],"iteration":328,"passed_time":1.474300163,"remaining_time":3.006855348},
{"learn":[281.9398292],"iteration":329,"passed_time":1.478262056,"remaining_time":3.001319932},
{"learn":[278.8749722],"iteration":330,"passed_time":1.480481924,"remaining_time":2.992273133},
{"learn":[278.0170821],"iteration":331,"passed_time":1.482215917,"remaining_time":2.982289858},
{"learn":[276.1771801],"iteration":332,"passed_time":1.483696041,"remaining_time":2.971847625},
{"learn":[274.232746],"iteration":333,"passed_time":1.485213733,"remaining_time":2.96153397},
{"learn":[273.6130173],"iteration":334,"passed_time":1.487193654,"remaining_time":2.952190388},
{"learn":[272.4993848],"iteration":335,"passed_time":1.489061337,"remaining_time":2.942668833},
{"learn":[271.9021231],"iteration":336,"passed_time":1.49099452,"remaining_time":2.933321563},
{"learn":[270.9757977],"iteration":337,"passed_time":1.492627445,"remaining_time":2.923430085},
{"learn":[268.4641753],"iteration":338,"passed_time":1.49511773,"remaining_time":2.915259054},
{"learn":[266.0064599],"iteration":339,"passed_time":1.496562208,"remaining_time":2.905091344},
{"learn":[265.1414871],"iteration":340,"passed_time":1.498406058,"remaining_time":2.895746604},
{"learn":[263.266109],"iteration":341,"passed_time":1.500454393,"remaining_time":2.886839153},
{"learn":[262.6914532],"iteration":342,"passed_time":1.501879471,"remaining_time":2.876777879},
{"learn":[260.5682066],"iteration":343,"passed_time":1.503240026,"remaining_time":2.86664377},
{"learn":[260.0021564],"iteration":344,"passed_time":1.504537877,"remaining_time":2.856441477},
{"learn":[257.933688],"iteration":345,"passed_time":1.508602286,"remaining_time":2.851519927},
{"learn":[257.3691481],"iteration":346,"passed_time":1.510911553,"remaining_time":2.843300416},
{"learn":[255.5277371],"iteration":347,"passed_time":1.513928166,"remaining_time":2.836440128},
{"learn":[253.8009444],"iteration":348,"passed_time":1.515652274,"remaining_time":2.827190919},
{"learn":[253.2603337],"iteration":349,"passed_time":1.517710229,"remaining_time":2.818604712},
{"learn":[252.3048903],"iteration":350,"passed_time":1.519879941,"remaining_time":2.810262341},
{"learn":[250.2574144],"iteration":351,"passed_time":1.522194369,"remaining_time":2.802221452},
{"learn":[248.6952026],"iteration":352,"passed_time":1.524158335,"remaining_time":2.793570659},
{"learn":[247.8650446],"iteration":353,"passed_time":1.528954613,"remaining_time":2.790126215},
{"learn":[247.3444311],"iteration":354,"passed_time":1.53133646,"remaining_time":2.782287372},
{"learn":[245.5439327],"iteration":355,"passed_time":1.540622346,"remaining_time":2.786968514},
{"learn":[245.0354763],"iteration":356,"passed_time":1.548757305,"remaining_time":2.789498451},
{"learn":[243.0773581],"iteration":357,"passed_time":1.552600943,"remaining_time":2.7842732},
{"learn":[240.9033208],"iteration":358,"passed_time":1.556260133,"remaining_time":2.778726309},
{"learn":[240.3526611],"iteration":359,"passed_time":1.561951701,"remaining_time":2.776803023},
{"learn":[238.1995122],"iteration":360,"passed_time":1.56533846,"remaining_time":2.770779157},
{"learn":[236.3225158],"iteration":361,"passed_time":1.570494705,"remaining_time":2.767888458},
{"learn":[235.8359686],"iteration":362,"passed_time":1.573023586,"remaining_time":2.760374723},
{"learn":[233.7709745],"iteration":363,"passed_time":1.57581726,"remaining_time":2.753351037},
{"learn":[231.9549393],"iteration":364,"passed_time":1.577809791,"remaining_time":2.744956759},
{"learn":[229.8753616],"iteration":365,"passed_time":1.581609162,"remaining_time":2.739727346},
{"learn":[229.3920229],"iteration":366,"passed_time":1.583809021,"remaining_time":2.731746895},
{"learn":[227.3495767],"iteration":367,"passed_time":1.58742325,"remaining_time":2.726226887},
{"learn":[225.9364058],"iteration":368,"passed_time":1.589502926,"remaining_time":2.71809308},
{"learn":[225.4261673],"iteration":369,"passed_time":1.591474574,"remaining_time":2.709808058},
{"learn":[224.9072755],"iteration":370,"passed_time":1.595675822,"remaining_time":2.705337175},
{"learn":[223.1771725],"iteration":371,"passed_time":1.597705616,"remaining_time":2.697201954},
{"learn":[221.2757476],"iteration":372,"passed_time":1.60118386,"remaining_time":2.691534263},
{"learn":[220.8203152],"iteration":373,"passed_time":1.603272361,"remaining_time":2.683552133},
{"learn":[218.8757761],"iteration":374,"passed_time":1.605509115,"remaining_time":2.675848525},
{"learn":[216.9429707],"iteration":375,"passed_time":1.607688299,"remaining_time":2.668078454},
{"learn":[216.4438811],"iteration":376,"passed_time":1.609520972,"remaining_time":2.659765426},
{"learn":[214.8302415],"iteration":377,"passed_time":1.613433981,"remaining_time":2.654909885},
{"learn":[213.2433872],"iteration":378,"passed_time":1.618036274,"remaining_time":2.651188723},
{"learn":[212.3026783],"iteration":379,"passed_time":1.621379758,"remaining_time":2.64540908},
{"learn":[210.6997612],"iteration":380,"passed_time":1.623662226,"remaining_time":2.63791842},
{"learn":[209.8262081],"iteration":381,"passed_time":1.628699788,"remaining_time":2.634912222},
{"learn":[208.0139133],"iteration":382,"passed_time":1.630821321,"remaining_time":2.627197794},
{"learn":[206.6572399],"iteration":383,"passed_time":1.635571035,"remaining_time":2.623728536},
{"learn":[206.183265],"iteration":384,"passed_time":1.637903442,"remaining_time":2.616391213},
{"learn":[204.3346147],"iteration":385,"passed_time":1.642414282,"remaining_time":2.612544998},
{"learn":[203.9262087],"iteration":386,"passed_time":1.649730042,"remaining_time":2.613138283},
{"learn":[202.1527009],"iteration":387,"passed_time":1.654910659,"remaining_time":2.610322998},
{"learn":[201.7517283],"iteration":388,"passed_time":1.658033344,"remaining_time":2.60426317},
{"learn":[200.2425128],"iteration":389,"passed_time":1.662176473,"remaining_time":2.599814484},
{"learn":[199.4224743],"iteration":390,"passed_time":1.664294167,"remaining_time":2.592212654},
{"learn":[198.0535009],"iteration":391,"passed_time":1.66843841,"remaining_time":2.587782023},
{"learn":[196.7430734],"iteration":392,"passed_time":1.670566778,"remaining_time":2.580239272},
{"learn":[196.2966525],"iteration":393,"passed_time":1.672273693,"remaining_time":2.572075782},
{"learn":[194.5576805],"iteration":394,"passed_time":1.674712981,"remaining_time":2.565066718},
{"learn":[194.1766907],"iteration":395,"passed_time":1.676061718,"remaining_time":2.556417367},
{"learn":[192.4053402],"iteration":396,"passed_time":1.677362337,"remaining_time":2.54773171},
{"learn":[192.0305942],"iteration":397,"passed_time":1.678676359,"remaining_time":2.539103437},
{"learn":[190.2944834],"iteration":398,"passed_time":1.681765682,"remaining_time":2.533185902},
{"learn":[189.9261091],"iteration":399,"passed_time":1.683423655,"remaining_time":2.525135483},
{"learn":[188.3142424],"iteration":400,"passed_time":1.684868269,"remaining_time":2.516798238},
{"learn":[186.977645],"iteration":401,"passed_time":1.68723367,"remaining_time":2.509865012},
{"learn":[186.6167551],"iteration":402,"passed_time":1.688747712,"remaining_time":2.501693261},
{"learn":[185.0424603],"iteration":403,"passed_time":1.69015685,"remaining_time":2.49339971},
{"learn":[183.489154],"iteration":404,"passed_time":1.691977674,"remaining_time":2.485744977},
{"learn":[182.9157142],"iteration":405,"passed_time":1.695024044,"remaining_time":2.479912025},
{"learn":[181.3859142],"iteration":406,"passed_time":1.696592827,"remaining_time":2.471939917},
{"learn":[180.8248722],"iteration":407,"passed_time":1.698359023,"remaining_time":2.464285641},
{"learn":[179.3181971],"iteration":408,"passed_time":1.702319075,"remaining_time":2.459830253},
{"learn":[178.7692632],"iteration":409,"passed_time":1.70470089,"remaining_time":2.453106158},
{"learn":[177.2514383],"iteration":410,"passed_time":1.70741623,"remaining_time":2.446881166},
{"learn":[176.7133971],"iteration":411,"passed_time":1.7091964,"remaining_time":2.439338552},
{"learn":[175.2183433],"iteration":412,"passed_time":1.71189938,"remaining_time":2.433135438},
{"learn":[174.8367375],"iteration":413,"passed_time":1.718379333,"remaining_time":2.432295384},
{"learn":[173.3892611],"iteration":414,"passed_time":1.722092795,"remaining_time":2.427528398},
{"learn":[172.8678654],"iteration":415,"passed_time":1.724359878,"remaining_time":2.420735983},
{"learn":[171.4132433],"iteration":416,"passed_time":1.72778155,"remaining_time":2.415579481},
{"learn":[170.0031178],"iteration":417,"passed_time":1.735797399,"remaining_time":2.416827958},
{"learn":[169.4926453],"iteration":418,"passed_time":1.744330766,"remaining_time":2.418749821},
{"learn":[168.1037731],"iteration":419,"passed_time":1.746517166,"remaining_time":2.411857039},
{"learn":[167.5678875],"iteration":420,"passed_time":1.751967791,"remaining_time":2.409475893},
{"learn":[166.1685734],"iteration":421,"passed_time":1.754995709,"remaining_time":2.403761896},
{"learn":[165.6747133],"iteration":422,"passed_time":1.756994218,"remaining_time":2.396656416},
{"learn":[164.3243439],"iteration":423,"passed_time":1.759140702,"remaining_time":2.389776048},
{"learn":[162.661061],"iteration":424,"passed_time":1.761750218,"remaining_time":2.383544413},
{"learn":[162.3068847],"iteration":425,"passed_time":1.763201368,"remaining_time":2.37576898},
{"learn":[161.7943954],"iteration":426,"passed_time":1.765455982,"remaining_time":2.369101352},
{"learn":[160.1734627],"iteration":427,"passed_time":1.767663921,"remaining_time":2.362391969},
{"learn":[159.828611],"iteration":428,"passed_time":1.769428925,"remaining_time":2.355114024},
{"learn":[159.529286],"iteration":429,"passed_time":1.771038361,"remaining_time":2.347655502},
{"learn":[157.9479778],"iteration":430,"passed_time":1.772355004,"remaining_time":2.339837581},
{"learn":[157.6541405],"iteration":431,"passed_time":1.774652079,"remaining_time":2.333338844},
{"learn":[157.1646787],"iteration":432,"passed_time":1.776801605,"remaining_time":2.326666305},
{"learn":[156.8765587],"iteration":433,"passed_time":1.778588497,"remaining_time":2.319541681},
{"learn":[155.5279964],"iteration":434,"passed_time":1.780871017,"remaining_time":2.313085344},
{"learn":[154.004277],"iteration":435,"passed_time":1.782349131,"remaining_time":2.305607591},
{"learn":[153.5555436],"iteration":436,"passed_time":1.784046769,"remaining_time":2.298440116},
{"learn":[153.2754756],"iteration":437,"passed_time":1.785509098,"remaining_time":2.290995692},
{"learn":[151.9746505],"iteration":438,"passed_time":1.789485104,"remaining_time":2.286790759},
{"learn":[151.5669758],"iteration":439,"passed_time":1.791546789,"remaining_time":2.280150458},
{"learn":[150.2739584],"iteration":440,"passed_time":1.794577943,"remaining_time":2.274759796},
{"learn":[150.0016951],"iteration":441,"passed_time":1.796638987,"remaining_time":2.268155101},
{"learn":[148.7458479],"iteration":442,"passed_time":1.799190498,"remaining_time":2.262187601},
{"learn":[148.2927725],"iteration":443,"passed_time":1.803450628,"remaining_time":2.258375111},
{"learn":[147.0669838],"iteration":444,"passed_time":1.806054349,"remaining_time":2.25249475},
{"learn":[146.4871026],"iteration":445,"passed_time":1.810316466,"remaining_time":2.248689063},
{"learn":[146.0995981],"iteration":446,"passed_time":1.813939721,"remaining_time":2.244090975},
{"learn":[144.9251866],"iteration":447,"passed_time":1.817441499,"remaining_time":2.239347562},
{"learn":[144.5135894],"iteration":448,"passed_time":1.821749736,"remaining_time":2.235599342},
{"learn":[143.3368483],"iteration":449,"passed_time":1.826435117,"remaining_time":2.232309587},
{"learn":[142.9327369],"iteration":450,"passed_time":1.829025087,"remaining_time":2.226462911},
{"learn":[142.3812247],"iteration":451,"passed_time":1.83333888,"remaining_time":2.222720589},
{"learn":[141.2502359],"iteration":452,"passed_time":1.835105929,"remaining_time":2.215900537},
{"learn":[140.8829924],"iteration":453,"passed_time":1.837066655,"remaining_time":2.209335669},
{"learn":[139.6374171],"iteration":454,"passed_time":1.840249212,"remaining_time":2.204254551},
{"learn":[138.2781919],"iteration":455,"passed_time":1.843048748,"remaining_time":2.198724822},
{"learn":[137.8924024],"iteration":456,"passed_time":1.846402187,"remaining_time":2.19386518},
{"learn":[137.4882931],"iteration":457,"passed_time":1.84823348,"remaining_time":2.187210799},
{"learn":[136.1654444],"iteration":458,"passed_time":1.850056196,"remaining_time":2.180567325},
{"learn":[135.7923296],"iteration":459,"passed_time":1.852397789,"remaining_time":2.174553926},
{"learn":[134.5025455],"iteration":460,"passed_time":1.85489763,"remaining_time":2.168741481},
{"learn":[134.1136081],"iteration":461,"passed_time":1.857046578,"remaining_time":2.162534759},
{"learn":[133.7302516],"iteration":462,"passed_time":1.859585975,"remaining_time":2.156798421},
{"learn":[132.4753968],"iteration":463,"passed_time":1.861186884,"remaining_time":2.149991746},
{"learn":[132.132348],"iteration":464,"passed_time":1.862516386,"remaining_time":2.142895196},
{"learn":[131.7581703],"iteration":465,"passed_time":1.864493128,"remaining_time":2.136565086},
{"learn":[130.6756588],"iteration":466,"passed_time":1.867354848,"remaining_time":2.13126367},
{"learn":[130.4313711],"iteration":467,"passed_time":1.869032723,"remaining_time":2.124626942},
{"learn":[130.0670163],"iteration":468,"passed_time":1.870531567,"remaining_time":2.117808661},
{"learn":[129.2607912],"iteration":469,"passed_time":1.874424846,"remaining_time":2.113713124},
{"learn":[129.0231563],"iteration":470,"passed_time":1.876944628,"remaining_time":2.108075814},
{"learn":[127.9152101],"iteration":471,"passed_time":1.879765818,"remaining_time":2.102788881},
{"learn":[126.8752095],"iteration":472,"passed_time":1.881328174,"remaining_time":2.096109826},
{"learn":[126.6446686],"iteration":473,"passed_time":1.884085454,"remaining_time":2.090778373},
{"learn":[125.4830214],"iteration":474,"passed_time":1.889288999,"remaining_time":2.088161525},
{"learn":[125.2512052],"iteration":475,"passed_time":1.892592549,"remaining_time":2.083442218},
{"learn":[125.0224033],"iteration":476,"passed_time":1.895473973,"remaining_time":2.078266013},
{"learn":[124.0233683],"iteration":477,"passed_time":1.897611996,"remaining_time":2.072287577},
{"learn":[123.7974205],"iteration":478,"passed_time":1.901107387,"remaining_time":2.067801563},
{"learn":[123.1694688],"iteration":479,"passed_time":1.907246186,"remaining_time":2.066183368},
{"learn":[122.9469682],"iteration":480,"passed_time":1.914680626,"remaining_time":2.065944376},
{"learn":[121.9731663],"iteration":481,"passed_time":1.92197071,"remaining_time":2.065520389},
{"learn":[121.154878],"iteration":482,"passed_time":1.923704155,"remaining_time":2.059120182},
{"learn":[120.5498356],"iteration":483,"passed_time":1.927225407,"remaining_time":2.054645269},
{"learn":[119.6065112],"iteration":484,"passed_time":1.929677669,"remaining_time":2.049039174},
{"learn":[119.4121257],"iteration":485,"passed_time":1.93195399,"remaining_time":2.043259982},
{"learn":[118.8177415],"iteration":486,"passed_time":1.934194096,"remaining_time":2.037457025},
{"learn":[117.8968673],"iteration":487,"passed_time":1.93580014,"remaining_time":2.031003426},
{"learn":[117.6868359],"iteration":488,"passed_time":1.937164014,"remaining_time":2.024316587},
{"learn":[117.1056836],"iteration":489,"passed_time":1.9405645,"remaining_time":2.019771215},
{"learn":[116.4108069],"iteration":490,"passed_time":1.942026736,"remaining_time":2.013221199},
{"learn":[115.5859451],"iteration":491,"passed_time":1.943537142,"remaining_time":2.006741602},
{"learn":[114.7017838],"iteration":492,"passed_time":1.944850593,"remaining_time":2.000079616},
{"learn":[114.4996496],"iteration":493,"passed_time":1.947732114,"remaining_time":1.995045445},
{"learn":[113.5389068],"iteration":494,"passed_time":1.950372782,"remaining_time":1.989774252},
{"learn":[113.3419679],"iteration":495,"passed_time":1.953289372,"remaining_time":1.984794039},
{"learn":[113.1473437],"iteration":496,"passed_time":1.954819595,"remaining_time":1.978419027},
{"learn":[112.2989987],"iteration":497,"passed_time":1.956346815,"remaining_time":1.972060444},
{"learn":[111.4299886],"iteration":498,"passed_time":1.957714096,"remaining_time":1.965560645},
{"learn":[111.2406142],"iteration":499,"passed_time":1.961308729,"remaining_time":1.961308729},
{"learn":[110.3653588],"iteration":500,"passed_time":1.962817072,"remaining_time":1.954981475},
{"learn":[110.1929009],"iteration":501,"passed_time":1.964169256,"remaining_time":1.948518505},
{"learn":[109.3030505],"iteration":502,"passed_time":1.967285811,"remaining_time":1.943819181},
{"learn":[109.0889241],"iteration":503,"passed_time":1.971003395,"remaining_time":1.939717627},
{"learn":[108.334025],"iteration":504,"passed_time":1.97334704,"remaining_time":1.934270861},
{"learn":[107.8146039],"iteration":505,"passed_time":1.974815622,"remaining_time":1.927982049},
{"learn":[106.9944531],"iteration":506,"passed_time":1.981042966,"remaining_time":1.92633961},
{"learn":[106.8176427],"iteration":507,"passed_time":1.983249555,"remaining_time":1.920785002},
{"learn":[106.0720174],"iteration":508,"passed_time":1.98729681,"remaining_time":1.917019123},
{"learn":[105.356334],"iteration":509,"passed_time":1.99051433,"remaining_time":1.912454945},
{"learn":[105.1837547],"iteration":510,"passed_time":1.994181568,"remaining_time":1.908326393},
{"learn":[104.6896156],"iteration":511,"passed_time":2.000319321,"remaining_time":1.906554353},
{"learn":[103.9254182],"iteration":512,"passed_time":2.00279649,"remaining_time":1.901290236},
{"learn":[103.1436231],"iteration":513,"passed_time":2.005448207,"remaining_time":1.896202002},
{"learn":[102.9771784],"iteration":514,"passed_time":2.009828694,"remaining_time":1.892751294},
{"learn":[102.3744579],"iteration":515,"passed_time":2.011276085,"remaining_time":1.886545785},
{"learn":[101.4944169],"iteration":516,"passed_time":2.015585119,"remaining_time":1.883032133},
{"learn":[101.2142629],"iteration":517,"passed_time":2.017388217,"remaining_time":1.877183631},
{"learn":[100.3516937],"iteration":518,"passed_time":2.020510898,"remaining_time":1.872573684},
{"learn":[100.077224],"iteration":519,"passed_time":2.02271137,"remaining_time":1.867118187},
{"learn":[99.23181326],"iteration":520,"passed_time":2.024306089,"remaining_time":1.861118266},
{"learn":[99.0715422],"iteration":521,"passed_time":2.027100351,"remaining_time":1.856233655},
{"learn":[98.60937844],"iteration":522,"passed_time":2.028633325,"remaining_time":1.850206685},
{"learn":[97.87225046],"iteration":523,"passed_time":2.030436568,"remaining_time":1.844442378},
{"learn":[97.60967352],"iteration":524,"passed_time":2.032287772,"remaining_time":1.838736555},
{"learn":[96.79206418],"iteration":525,"passed_time":2.034048916,"remaining_time":1.832964233},
{"learn":[96.638616],"iteration":526,"passed_time":2.035393216,"remaining_time":1.826833001},
{"learn":[96.38235236],"iteration":527,"passed_time":2.037805259,"remaining_time":1.821674398},
{"learn":[95.81950813],"iteration":528,"passed_time":2.040492076,"remaining_time":1.816770828},
{"learn":[95.02429915],"iteration":529,"passed_time":2.042254339,"remaining_time":1.811055735},
{"learn":[94.50634575],"iteration":530,"passed_time":2.043694644,"remaining_time":1.805071164},
{"learn":[93.73001612],"iteration":531,"passed_time":2.046309371,"remaining_time":1.800136815},
{"learn":[92.96793815],"iteration":532,"passed_time":2.048119409,"remaining_time":1.794506124},
{"learn":[92.23652959],"iteration":533,"passed_time":2.04955473,"remaining_time":1.788562742},
{"learn":[91.5166515],"iteration":534,"passed_time":2.050892935,"remaining_time":1.782551803},
{"learn":[91.37155264],"iteration":535,"passed_time":2.054317487,"remaining_time":1.778364392},
{"learn":[91.22835767],"iteration":536,"passed_time":2.058450204,"remaining_time":1.7747904},
{"learn":[90.74048749],"iteration":537,"passed_time":2.061077987,"remaining_time":1.769921989},
{"learn":[89.98622261],"iteration":538,"passed_time":2.063023638,"remaining_time":1.764478474},
{"learn":[89.28329703],"iteration":539,"passed_time":2.067508561,"remaining_time":1.761210996},
{"learn":[88.64135667],"iteration":540,"passed_time":2.069589736,"remaining_time":1.755899609},
{"learn":[88.19360655],"iteration":541,"passed_time":2.072238356,"remaining_time":1.751079644},
{"learn":[87.75496133],"iteration":542,"passed_time":2.075263806,"remaining_time":1.746584824},
{"learn":[87.3765657],"iteration":543,"passed_time":2.078230805,"remaining_time":1.74204641},
{"learn":[86.63267539],"iteration":544,"passed_time":2.082205721,"remaining_time":1.738355235},
{"learn":[86.20328925],"iteration":545,"passed_time":2.08648499,"remaining_time":1.73491609},
{"learn":[85.58014444],"iteration":546,"passed_time":2.087998429,"remaining_time":1.729183343},
{"learn":[85.06227511],"iteration":547,"passed_time":2.089777553,"remaining_time":1.723685135},
{"learn":[84.46013936],"iteration":548,"passed_time":2.093017246,"remaining_time":1.719400324},
{"learn":[83.88010966],"iteration":549,"passed_time":2.095682167,"remaining_time":1.714649045},
{"learn":[83.47322539],"iteration":550,"passed_time":2.098341191,"remaining_time":1.709900535},
{"learn":[83.32110131],"iteration":551,"passed_time":2.100418726,"remaining_time":1.704687662},
{"learn":[82.72822539],"iteration":552,"passed_time":2.10215459,"remaining_time":1.699209949},
{"learn":[82.57890469],"iteration":553,"passed_time":2.103509581,"remaining_time":1.693439121},
{"learn":[82.10241169],"iteration":554,"passed_time":2.106650342,"remaining_time":1.68911604},
{"learn":[81.68449036],"iteration":555,"passed_time":2.108018032,"remaining_time":1.683381306},
{"learn":[80.8584122],"iteration":556,"passed_time":2.109412587,"remaining_time":1.67768362},
{"learn":[80.29461409],"iteration":557,"passed_time":2.110711926,"remaining_time":1.671925934},
{"learn":[79.77047458],"iteration":558,"passed_time":2.114306537,"remaining_time":1.66799496},
{"learn":[79.38149124],"iteration":559,"passed_time":2.115723203,"remaining_time":1.662353945},
{"learn":[78.74275673],"iteration":560,"passed_time":2.117022849,"remaining_time":1.656636418},
{"learn":[78.57037484],"iteration":561,"passed_time":2.120400109,"remaining_time":1.652553822},
{"learn":[77.94686636],"iteration":562,"passed_time":2.122282529,"remaining_time":1.647313437},
{"learn":[77.75966369],"iteration":563,"passed_time":2.123821179,"remaining_time":1.641819209},
{"learn":[77.57512623],"iteration":564,"passed_time":2.12627479,"remaining_time":1.637043422},
{"learn":[77.13282808],"iteration":565,"passed_time":2.127722483,"remaining_time":1.631504519},
{"learn":[76.74684384],"iteration":566,"passed_time":2.129131505,"remaining_time":1.625950514},
{"learn":[75.98398507],"iteration":567,"passed_time":2.130478803,"remaining_time":1.62036416},
{"learn":[75.8056417],"iteration":568,"passed_time":2.13295985,"remaining_time":1.615651486},
{"learn":[75.30018621],"iteration":569,"passed_time":2.134401252,"remaining_time":1.610162348},
{"learn":[75.12432317],"iteration":570,"passed_time":2.136778504,"remaining_time":1.605390505},
{"learn":[74.61019375],"iteration":571,"passed_time":2.140902683,"remaining_time":1.601934176},
{"learn":[74.25648565],"iteration":572,"passed_time":2.143020376,"remaining_time":1.59698028},
{"learn":[73.75833607],"iteration":573,"passed_time":2.14581878,"remaining_time":1.592541464},
{"learn":[73.14171549],"iteration":574,"passed_time":2.14786333,"remaining_time":1.587551157},
{"learn":[73.04536167],"iteration":575,"passed_time":2.14977709,"remaining_time":1.582474803},
{"learn":[72.47479388],"iteration":576,"passed_time":2.155039853,"remaining_time":1.579864572},
{"learn":[72.38024262],"iteration":577,"passed_time":2.16063675,"remaining_time":1.577489115},
{"learn":[71.82252318],"iteration":578,"passed_time":2.163605033,"remaining_time":1.573191225},
{"learn":[71.67595467],"iteration":579,"passed_time":2.167347647,"remaining_time":1.569458641},
{"learn":[71.13131868],"iteration":580,"passed_time":2.170578522,"remaining_time":1.565356972},
{"learn":[71.03989767],"iteration":581,"passed_time":2.175326249,"remaining_time":1.562347718},
{"learn":[70.64202204],"iteration":582,"passed_time":2.177860269,"remaining_time":1.557749112},
{"learn":[69.95071318],"iteration":583,"passed_time":2.180948481,"remaining_time":1.553552342},
{"learn":[69.72643775],"iteration":584,"passed_time":2.187420632,"remaining_time":1.551759935},
{"learn":[69.44117595],"iteration":585,"passed_time":2.190293725,"remaining_time":1.547408877},
{"learn":[68.87643154],"iteration":586,"passed_time":2.194261049,"remaining_time":1.543832731},
{"learn":[68.21027352],"iteration":587,"passed_time":2.196214757,"remaining_time":1.538844354},
{"learn":[68.068673],"iteration":588,"passed_time":2.199170739,"remaining_time":1.53456566},
{"learn":[67.79389019],"iteration":589,"passed_time":2.201869101,"remaining_time":1.530112426},
{"learn":[67.24590627],"iteration":590,"passed_time":2.203321265,"remaining_time":1.524802703},
{"learn":[66.69917938],"iteration":591,"passed_time":2.205346691,"remaining_time":1.519901098},
{"learn":[66.17263462],"iteration":592,"passed_time":2.208222005,"remaining_time":1.515592506},
{"learn":[65.65331011],"iteration":593,"passed_time":2.209660162,"remaining_time":1.510306441},
{"learn":[65.22855798],"iteration":594,"passed_time":2.212572038,"remaining_time":1.506036429},
{"learn":[64.71133708],"iteration":595,"passed_time":2.214620115,"remaining_time":1.501185447},
{"learn":[64.49345526],"iteration":596,"passed_time":2.216100215,"remaining_time":1.495960447},
{"learn":[64.27978375],"iteration":597,"passed_time":2.217427837,"remaining_time":1.490645469},
{"learn":[63.80035409],"iteration":598,"passed_time":2.219917353,"remaining_time":1.486121634},
{"learn":[63.39166064],"iteration":599,"passed_time":2.221373505,"remaining_time":1.48091567},
{"learn":[63.18498937],"iteration":600,"passed_time":2.222969812,"remaining_time":1.475815233},
{"learn":[62.98227013],"iteration":601,"passed_time":2.224940955,"remaining_time":1.470974253},
{"learn":[62.50280606],"iteration":602,"passed_time":2.227110781,"remaining_time":1.466273599},
{"learn":[62.06392546],"iteration":603,"passed_time":2.228521306,"remaining_time":1.461083505},
{"learn":[61.84850982],"iteration":604,"passed_time":2.229971105,"remaining_time":1.455931548},
{"learn":[61.37779131],"iteration":605,"passed_time":2.23273521,"remaining_time":1.451646325},
{"learn":[60.88749952],"iteration":606,"passed_time":2.234791382,"remaining_time":1.446907764},
{"learn":[60.55391858],"iteration":607,"passed_time":2.238819899,"remaining_time":1.443449671},
{"learn":[60.03232485],"iteration":608,"passed_time":2.240283214,"remaining_time":1.438342753},
{"learn":[59.56430732],"iteration":609,"passed_time":2.241841053,"remaining_time":1.433308215},
{"learn":[59.35984052],"iteration":610,"passed_time":2.248394017,"remaining_time":1.431465258},
{"learn":[58.89222027],"iteration":611,"passed_time":2.252987936,"remaining_time":1.428364901},
{"learn":[58.57228548],"iteration":612,"passed_time":2.256682952,"remaining_time":1.424692174},
{"learn":[58.37416497],"iteration":613,"passed_time":2.270091364,"remaining_time":1.427125841},
{"learn":[57.87859662],"iteration":614,"passed_time":2.274412548,"remaining_time":1.423819237},
{"learn":[57.44199224],"iteration":615,"passed_time":2.283509382,"remaining_time":1.423486368},
{"learn":[57.01594048],"iteration":616,"passed_time":2.289936997,"remaining_time":1.421468184},
{"learn":[56.65724092],"iteration":617,"passed_time":2.292731603,"remaining_time":1.417190085},
{"learn":[56.25519992],"iteration":618,"passed_time":2.29675944,"remaining_time":1.413675843},
{"learn":[55.89458997],"iteration":619,"passed_time":2.300684968,"remaining_time":1.410097238},
{"learn":[55.5442678],"iteration":620,"passed_time":2.303095365,"remaining_time":1.405592824},
{"learn":[55.16832612],"iteration":621,"passed_time":2.305700036,"remaining_time":1.401213205},
{"learn":[54.90995293],"iteration":622,"passed_time":2.31196732,"remaining_time":1.399055665},
{"learn":[54.54223027],"iteration":623,"passed_time":2.315958826,"remaining_time":1.395513652},
{"learn":[54.11190564],"iteration":624,"passed_time":2.330188696,"remaining_time":1.398113218},
{"learn":[53.60177783],"iteration":625,"passed_time":2.346829476,"remaining_time":1.4020994},
{"learn":[53.42454833],"iteration":626,"passed_time":2.361470941,"remaining_time":1.4048304},
{"learn":[53.16443821],"iteration":627,"passed_time":2.376701772,"remaining_time":1.40785519},
{"learn":[52.96028072],"iteration":628,"passed_time":2.392222349,"remaining_time":1.410992833},
{"learn":[52.56217189],"iteration":629,"passed_time":2.397702183,"remaining_time":1.408174298},
{"learn":[52.21641973],"iteration":630,"passed_time":2.401406423,"remaining_time":1.404308986},
{"learn":[51.79976806],"iteration":631,"passed_time":2.415669937,"remaining_time":1.406592621},
{"learn":[51.39748776],"iteration":632,"passed_time":2.419057369,"remaining_time":1.402518253},
{"learn":[51.16998879],"iteration":633,"passed_time":2.420925732,"remaining_time":1.397569113},
{"learn":[50.80163563],"iteration":634,"passed_time":2.423449911,"remaining_time":1.393006642},
{"learn":[50.40819351],"iteration":635,"passed_time":2.427802332,"remaining_time":1.389496932},
{"learn":[50.02328438],"iteration":636,"passed_time":2.430925356,"remaining_time":1.385283994},
{"learn":[49.80576853],"iteration":637,"passed_time":2.434855003,"remaining_time":1.381532149},
{"learn":[49.42928599],"iteration":638,"passed_time":2.437451873,"remaining_time":1.377026801},
{"learn":[49.05254372],"iteration":639,"passed_time":2.441029814,"remaining_time":1.37307927},
{"learn":[48.75584716],"iteration":640,"passed_time":2.445472399,"remaining_time":1.369617147},
{"learn":[48.30176507],"iteration":641,"passed_time":2.450498297,"remaining_time":1.366477244},
{"learn":[47.9384765],"iteration":642,"passed_time":2.453672636,"remaining_time":1.36230347},
{"learn":[47.56406952],"iteration":643,"passed_time":2.458183531,"remaining_time":1.358871641},
{"learn":[47.21149415],"iteration":644,"passed_time":2.463772858,"remaining_time":1.356030022},
{"learn":[47.00565099],"iteration":645,"passed_time":2.467543396,"remaining_time":1.352183223},
{"learn":[46.64420501],"iteration":646,"passed_time":2.470439577,"remaining_time":1.347859615},
{"learn":[46.36762987],"iteration":647,"passed_time":2.4768766,"remaining_time":1.345463832},
{"learn":[46.17454348],"iteration":648,"passed_time":2.483881423,"remaining_time":1.34336268},
{"learn":[45.87586444],"iteration":649,"passed_time":2.486408267,"remaining_time":1.338835221},
{"learn":[45.45834215],"iteration":650,"passed_time":2.488726365,"remaining_time":1.334201999},
{"learn":[45.12745],"iteration":651,"passed_time":2.491668373,"remaining_time":1.329908886},
{"learn":[44.93167888],"iteration":652,"passed_time":2.497803897,"remaining_time":1.327316925},
{"learn":[44.52851923],"iteration":653,"passed_time":2.502677043,"remaining_time":1.324046264},
{"learn":[44.23961949],"iteration":654,"passed_time":2.504151693,"remaining_time":1.318980663},
{"learn":[44.0501487],"iteration":655,"passed_time":2.506585082,"remaining_time":1.314428763},
{"learn":[43.7208103],"iteration":656,"passed_time":2.51524754,"remaining_time":1.313135322},
{"learn":[43.42109848],"iteration":657,"passed_time":2.517525214,"remaining_time":1.308500947},
{"learn":[43.23898162],"iteration":658,"passed_time":2.519089344,"remaining_time":1.303504501},
{"learn":[42.96218963],"iteration":659,"passed_time":2.523683081,"remaining_time":1.300079163},
{"learn":[42.64813166],"iteration":660,"passed_time":2.525151505,"remaining_time":1.295047444},
{"learn":[42.27060636],"iteration":661,"passed_time":2.527065979,"remaining_time":1.290254231},
{"learn":[42.05004459],"iteration":662,"passed_time":2.529820916,"remaining_time":1.285896906},
{"learn":[41.90323102],"iteration":663,"passed_time":2.531353775,"remaining_time":1.280926007},
{"learn":[41.7389187],"iteration":664,"passed_time":2.532670137,"remaining_time":1.275856385},
{"learn":[41.37335706],"iteration":665,"passed_time":2.536242266,"remaining_time":1.271929305},
{"learn":[41.16262665],"iteration":666,"passed_time":2.538272798,"remaining_time":1.267233646},
{"learn":[40.9010975],"iteration":667,"passed_time":2.540604626,"remaining_time":1.262695713},
{"learn":[40.739436],"iteration":668,"passed_time":2.542172089,"remaining_time":1.257786191},
{"learn":[40.47369462],"iteration":669,"passed_time":2.544721264,"remaining_time":1.253370175},
{"learn":[40.27644787],"iteration":670,"passed_time":2.549266163,"remaining_time":1.249938253},
{"learn":[39.96016303],"iteration":671,"passed_time":2.550895652,"remaining_time":1.245080021},
{"learn":[39.76816877],"iteration":672,"passed_time":2.553071755,"remaining_time":1.240496974},
{"learn":[39.61293844],"iteration":673,"passed_time":2.55674352,"remaining_time":1.236644492},
{"learn":[39.45832968],"iteration":674,"passed_time":2.55968721,"remaining_time":1.23244199},
{"learn":[39.38934932],"iteration":675,"passed_time":2.56959229,"remaining_time":1.231579737},
{"learn":[39.13624606],"iteration":676,"passed_time":2.576426597,"remaining_time":1.229225688},
{"learn":[39.0682852],"iteration":677,"passed_time":2.578498964,"remaining_time":1.224596853},
{"learn":[38.82516313],"iteration":678,"passed_time":2.58356266,"remaining_time":1.221389711},
{"learn":[38.57730702],"iteration":679,"passed_time":2.587799747,"remaining_time":1.217788116},
{"learn":[38.39597633],"iteration":680,"passed_time":2.590866335,"remaining_time":1.213636359},
{"learn":[38.15232597],"iteration":681,"passed_time":2.594230466,"remaining_time":1.209626522},
{"learn":[37.91091118],"iteration":682,"passed_time":2.59673155,"remaining_time":1.205218011},
{"learn":[37.83335882],"iteration":683,"passed_time":2.60464973,"remaining_time":1.203317711},
{"learn":[37.75684985],"iteration":684,"passed_time":2.609128402,"remaining_time":1.19981817},
{"learn":[37.46374412],"iteration":685,"passed_time":2.610856232,"remaining_time":1.195056642},
{"learn":[37.29802326],"iteration":686,"passed_time":2.61496159,"remaining_time":1.191387158},
{"learn":[37.12702667],"iteration":687,"passed_time":2.616524493,"remaining_time":1.186563433},
{"learn":[37.05250687],"iteration":688,"passed_time":2.617846068,"remaining_time":1.181640242},
{"learn":[36.72975584],"iteration":689,"passed_time":2.621030682,"remaining_time":1.177564509},
{"learn":[36.47147503],"iteration":690,"passed_time":2.623992623,"remaining_time":1.173391781},
{"learn":[36.30209035],"iteration":691,"passed_time":2.627025621,"remaining_time":1.169254178},
{"learn":[35.98896321],"iteration":692,"passed_time":2.62987342,"remaining_time":1.16503772},
{"learn":[35.82765479],"iteration":693,"passed_time":2.631325251,"remaining_time":1.160209693},
{"learn":[35.61769821],"iteration":694,"passed_time":2.634074949,"remaining_time":1.155960949},
{"learn":[35.39806698],"iteration":695,"passed_time":2.636995947,"remaining_time":1.151791333},
{"learn":[35.09285674],"iteration":696,"passed_time":2.638563528,"remaining_time":1.147036942},
{"learn":[34.79328157],"iteration":697,"passed_time":2.642079342,"remaining_time":1.143134615},
{"learn":[34.46844603],"iteration":698,"passed_time":2.644744374,"remaining_time":1.138867034},
{"learn":[34.19972235],"iteration":699,"passed_time":2.646483387,"remaining_time":1.134207166},
{"learn":[33.9083775],"iteration":700,"passed_time":2.655855025,"remaining_time":1.132811202},
{"learn":[33.59674256],"iteration":701,"passed_time":2.658094094,"remaining_time":1.128364729},
{"learn":[33.31285423],"iteration":702,"passed_time":2.663269209,"remaining_time":1.125164943},
{"learn":[33.03206491],"iteration":703,"passed_time":2.666660764,"remaining_time":1.121209639},
{"learn":[32.75143157],"iteration":704,"passed_time":2.670686145,"remaining_time":1.117521153},
{"learn":[32.47855172],"iteration":705,"passed_time":2.674995939,"remaining_time":1.11395015},
{"learn":[32.29865379],"iteration":706,"passed_time":2.677435907,"remaining_time":1.109602151},
{"learn":[32.02721508],"iteration":707,"passed_time":2.68360595,"remaining_time":1.106797934},
{"learn":[31.76368749],"iteration":708,"passed_time":2.685866965,"remaining_time":1.102379812},
{"learn":[31.4802497],"iteration":709,"passed_time":2.688293057,"remaining_time":1.098035192},
{"learn":[31.21808503],"iteration":710,"passed_time":2.696343209,"remaining_time":1.09598198},
{"learn":[30.93733758],"iteration":711,"passed_time":2.70149413,"remaining_time":1.092739199},
{"learn":[30.68573458],"iteration":712,"passed_time":2.703092423,"remaining_time":1.088061046},
{"learn":[30.41767708],"iteration":713,"passed_time":2.707575726,"remaining_time":1.08454714},
{"learn":[30.36641655],"iteration":714,"passed_time":2.71435315,"remaining_time":1.081944962},
{"learn":[30.14436957],"iteration":715,"passed_time":2.717153083,"remaining_time":1.077753458},
{"learn":[29.93287852],"iteration":716,"passed_time":2.72090476,"remaining_time":1.073941488},
{"learn":[29.71324974],"iteration":717,"passed_time":2.72235296,"remaining_time":1.069224979},
{"learn":[29.46503823],"iteration":718,"passed_time":2.728475618,"remaining_time":1.066344435},
{"learn":[29.26005218],"iteration":719,"passed_time":2.731457391,"remaining_time":1.06223343},
{"learn":[29.05908724],"iteration":720,"passed_time":2.73632944,"remaining_time":1.058857023},
{"learn":[28.8616704],"iteration":721,"passed_time":2.738367782,"remaining_time":1.054385379},
{"learn":[28.67624666],"iteration":722,"passed_time":2.740142679,"remaining_time":1.049819533},
{"learn":[28.48640181],"iteration":723,"passed_time":2.743046427,"remaining_time":1.045691732},
{"learn":[28.32240863],"iteration":724,"passed_time":2.75469188,"remaining_time":1.044883127},
{"learn":[28.11908297],"iteration":725,"passed_time":2.756975782,"remaining_time":1.040511521},
{"learn":[27.91667982],"iteration":726,"passed_time":2.759753239,"remaining_time":1.036330996},
{"learn":[27.76776762],"iteration":727,"passed_time":2.772451191,"remaining_time":1.035860885},
{"learn":[27.6097697],"iteration":728,"passed_time":2.77484844,"remaining_time":1.031528021},
{"learn":[27.47419796],"iteration":729,"passed_time":2.777045351,"remaining_time":1.027126363},
{"learn":[27.31082731],"iteration":730,"passed_time":2.77884291,"remaining_time":1.02258378},
{"learn":[27.08865294],"iteration":731,"passed_time":2.793614807,"remaining_time":1.022798864},
{"learn":[26.94625788],"iteration":732,"passed_time":2.795258276,"remaining_time":1.018190941},
{"learn":[26.77056977],"iteration":733,"passed_time":2.79674701,"remaining_time":1.01353502},
{"learn":[26.64111634],"iteration":734,"passed_time":2.798702885,"remaining_time":1.009056142},
{"learn":[26.50200894],"iteration":735,"passed_time":2.811368532,"remaining_time":1.008425669},
{"learn":[26.29717067],"iteration":736,"passed_time":2.814603646,"remaining_time":1.004397231},
{"learn":[26.09703804],"iteration":737,"passed_time":2.816178858,"remaining_time":0.9997816543},
{"learn":[25.88297286],"iteration":738,"passed_time":2.817697051,"remaining_time":0.9951541681},
{"learn":[25.69644036],"iteration":739,"passed_time":2.819953886,"remaining_time":0.9907946084},
{"learn":[25.54552478],"iteration":740,"passed_time":2.832723585,"remaining_time":0.9901152611},
{"learn":[25.34474818],"iteration":741,"passed_time":2.835599156,"remaining_time":0.9859630487},
{"learn":[25.16384883],"iteration":742,"passed_time":2.837191378,"remaining_time":0.9813703691},
{"learn":[25.03571853],"iteration":743,"passed_time":2.838691883,"remaining_time":0.9767541964},
{"learn":[24.82435356],"iteration":744,"passed_time":2.853076865,"remaining_time":0.9765565107},
{"learn":[24.62471008],"iteration":745,"passed_time":2.856002063,"remaining_time":0.9724189331},
{"learn":[24.41939893],"iteration":746,"passed_time":2.85832537,"remaining_time":0.9680807479},
{"learn":[24.24830662],"iteration":747,"passed_time":2.872412482,"remaining_time":0.967711157},
{"learn":[24.08162908],"iteration":748,"passed_time":2.874836554,"remaining_time":0.9633964953},
{"learn":[23.91920194],"iteration":749,"passed_time":2.889141319,"remaining_time":0.9630471065},
{"learn":[23.76546501],"iteration":750,"passed_time":2.903094789,"remaining_time":0.9625440777},
{"learn":[23.63891657],"iteration":751,"passed_time":2.904938801,"remaining_time":0.9580117323},
{"learn":[23.49308583],"iteration":752,"passed_time":2.906388491,"remaining_time":0.953357181},
{"learn":[23.33094272],"iteration":753,"passed_time":2.919673504,"remaining_time":0.9525725224},
{"learn":[23.20904585],"iteration":754,"passed_time":2.921412328,"remaining_time":0.9480079738},
{"learn":[23.07654646],"iteration":755,"passed_time":2.934530132,"remaining_time":0.9471234816},
{"learn":[22.94762928],"iteration":756,"passed_time":2.937911835,"remaining_time":0.9430813421},
{"learn":[22.83314104],"iteration":757,"passed_time":2.950441989,"remaining_time":0.9419616906},
{"learn":[22.68379571],"iteration":758,"passed_time":2.95246113,"remaining_time":0.9374744826},
{"learn":[22.49845316],"iteration":759,"passed_time":2.954584265,"remaining_time":0.9330266098},
{"learn":[22.31671384],"iteration":760,"passed_time":2.966588999,"remaining_time":0.9316882665},
{"learn":[22.16235937],"iteration":761,"passed_time":2.969138475,"remaining_time":0.92736871},
{"learn":[22.01059975],"iteration":762,"passed_time":2.981949469,"remaining_time":0.9262411851},
{"learn":[21.92944821],"iteration":763,"passed_time":2.983534813,"remaining_time":0.9216154659},
{"learn":[21.756655],"iteration":764,"passed_time":2.985128853,"remaining_time":0.9170003667},
{"learn":[21.67806318],"iteration":765,"passed_time":2.986551002,"remaining_time":0.9123406455},
{"learn":[21.50929389],"iteration":766,"passed_time":2.987894555,"remaining_time":0.9076654906},
{"learn":[21.4331842],"iteration":767,"passed_time":3.00060273,"remaining_time":0.9064320748},
{"learn":[21.262938],"iteration":768,"passed_time":3.003486465,"remaining_time":0.9022176506},
{"learn":[21.11439161],"iteration":769,"passed_time":3.005223326,"remaining_time":0.8976641104},
{"learn":[20.9543844],"iteration":770,"passed_time":3.018184664,"remaining_time":0.8964517356},
{"learn":[20.80930318],"iteration":771,"passed_time":3.019786486,"remaining_time":0.89185404},
{"learn":[20.7063516],"iteration":772,"passed_time":3.021231386,"remaining_time":0.8872180137},
{"learn":[20.63428483],"iteration":773,"passed_time":3.033739168,"remaining_time":0.8858204806},
{"learn":[20.49331611],"iteration":774,"passed_time":3.035907335,"remaining_time":0.8813924521},
{"learn":[20.35495956],"iteration":775,"passed_time":3.038016341,"remaining_time":0.8769531707},
{"learn":[20.25248501],"iteration":776,"passed_time":3.052154868,"remaining_time":0.8759723752},
{"learn":[20.11761649],"iteration":777,"passed_time":3.054109391,"remaining_time":0.8714810858},
{"learn":[19.9874334],"iteration":778,"passed_time":3.065787881,"remaining_time":0.8697549701},
{"learn":[19.9231066],"iteration":779,"passed_time":3.068994288,"remaining_time":0.8656137736},
{"learn":[19.7924689],"iteration":780,"passed_time":3.082011997,"remaining_time":0.8642261553},
{"learn":[19.66544535],"iteration":781,"passed_time":3.083868986,"remaining_time":0.8596974922},
{"learn":[19.61593388],"iteration":782,"passed_time":3.085804973,"remaining_time":0.8551975469},
{"learn":[19.48769773],"iteration":783,"passed_time":3.097293087,"remaining_time":0.8533358505},
{"learn":[19.35159527],"iteration":784,"passed_time":3.101266585,"remaining_time":0.849391485},
{"learn":[19.2169088],"iteration":785,"passed_time":3.103338765,"remaining_time":0.844929384},
{"learn":[19.11576644],"iteration":786,"passed_time":3.104888615,"remaining_time":0.8403319886},
{"learn":[19.00257584],"iteration":787,"passed_time":3.111180703,"remaining_time":0.8370181586},
{"learn":[18.88320428],"iteration":788,"passed_time":3.11916362,"remaining_time":0.8341489527},
{"learn":[18.77089033],"iteration":789,"passed_time":3.121219315,"remaining_time":0.8296912103},
{"learn":[18.72786911],"iteration":790,"passed_time":3.123321376,"remaining_time":0.825251792},
{"learn":[18.60577775],"iteration":791,"passed_time":3.125315303,"remaining_time":0.8207898776},
{"learn":[18.56348401],"iteration":792,"passed_time":3.135208359,"remaining_time":0.818396129},
{"learn":[18.41802591],"iteration":793,"passed_time":3.141621237,"remaining_time":0.8150805728},
{"learn":[18.3765858],"iteration":794,"passed_time":3.157629408,"remaining_time":0.8142314825},
{"learn":[18.25018855],"iteration":795,"passed_time":3.160775243,"remaining_time":0.8100479267},
{"learn":[18.14369988],"iteration":796,"passed_time":3.172024483,"remaining_time":0.8079309535},
{"learn":[18.04118248],"iteration":797,"passed_time":3.17694165,"remaining_time":0.8041882372},
{"learn":[17.94013889],"iteration":798,"passed_time":3.185653096,"remaining_time":0.8013970868},
{"learn":[17.90039316],"iteration":799,"passed_time":3.193345185,"remaining_time":0.7983362963},
{"learn":[17.86116154],"iteration":800,"passed_time":3.194800613,"remaining_time":0.7937145092},
{"learn":[17.71907519],"iteration":801,"passed_time":3.196429286,"remaining_time":0.7891433897},
{"learn":[17.68061511],"iteration":802,"passed_time":3.2058334,"remaining_time":0.786487148},
{"learn":[17.55567257],"iteration":803,"passed_time":3.220971886,"remaining_time":0.7852120518},
{"learn":[17.43729313],"iteration":804,"passed_time":3.22326667,"remaining_time":0.7807913051},
{"learn":[17.3257683],"iteration":805,"passed_time":3.238474866,"remaining_time":0.7794840248},
{"learn":[17.22975548],"iteration":806,"passed_time":3.24076893,"remaining_time":0.7750537838},
{"learn":[17.19247803],"iteration":807,"passed_time":3.253961636,"remaining_time":0.7732186066},
{"learn":[17.15568056],"iteration":808,"passed_time":3.256176285,"remaining_time":0.7687634988},
{"learn":[17.02499745],"iteration":809,"passed_time":3.258273821,"remaining_time":0.7642864519},
{"learn":[16.94152167],"iteration":810,"passed_time":3.260570807,"remaining_time":0.7598617541},
{"learn":[16.83502518],"iteration":811,"passed_time":3.271089937,"remaining_time":0.757345946},
{"learn":[16.79871816],"iteration":812,"passed_time":3.275210086,"remaining_time":0.7533386053},
{"learn":[16.76287813],"iteration":813,"passed_time":3.277891865,"remaining_time":0.749002318},
{"learn":[16.64978929],"iteration":814,"passed_time":3.29262357,"remaining_time":0.7474053502},
{"learn":[16.55601537],"iteration":815,"passed_time":3.295468329,"remaining_time":0.7430957997},
{"learn":[16.45830268],"iteration":816,"passed_time":3.297600484,"remaining_time":0.7386302186},
{"learn":[16.37922988],"iteration":817,"passed_time":3.312632935,"remaining_time":0.7370405797},
{"learn":[16.34411002],"iteration":818,"passed_time":3.31423959,"remaining_time":0.732450996},
{"learn":[16.27321446],"iteration":819,"passed_time":3.330048251,"remaining_time":0.7309862014},
{"learn":[16.19588531],"iteration":820,"passed_time":3.332070509,"remaining_time":0.7264806592},
{"learn":[16.16128642],"iteration":821,"passed_time":3.345240055,"remaining_time":0.7243950484},
{"learn":[16.06037245],"iteration":822,"passed_time":3.348473975,"remaining_time":0.7201456788},
{"learn":[15.96717061],"iteration":823,"passed_time":3.357077969,"remaining_time":0.7170457798},
{"learn":[15.9082898],"iteration":824,"passed_time":3.364415523,"remaining_time":0.7136638989},
{"learn":[15.87429861],"iteration":825,"passed_time":3.368382342,"remaining_time":0.709562382},
{"learn":[15.78552057],"iteration":826,"passed_time":3.371933208,"remaining_time":0.7053741778},
{"learn":[15.67757046],"iteration":827,"passed_time":3.382431922,"remaining_time":0.7026307858},
{"learn":[15.60459647],"iteration":828,"passed_time":3.391069397,"remaining_time":0.6994847611},
{"learn":[15.57129637],"iteration":829,"passed_time":3.397334191,"remaining_time":0.6958395331},
{"learn":[15.49269801],"iteration":830,"passed_time":3.399596532,"remaining_time":0.6913740239},
{"learn":[15.40236637],"iteration":831,"passed_time":3.402783847,"remaining_time":0.6871005845},
{"learn":[15.32043135],"iteration":832,"passed_time":3.408564279,"remaining_time":0.6833496213},
{"learn":[15.22814317],"iteration":833,"passed_time":3.410867553,"remaining_time":0.6789016953},
{"learn":[15.17387283],"iteration":834,"passed_time":3.414168255,"remaining_time":0.6746560025},
{"learn":[15.07040204],"iteration":835,"passed_time":3.416174603,"remaining_time":0.6701586542},
{"learn":[14.97176735],"iteration":836,"passed_time":3.421106627,"remaining_time":0.6662370134},
{"learn":[14.86065393],"iteration":837,"passed_time":3.429981092,"remaining_time":0.6630751036},
{"learn":[14.76946619],"iteration":838,"passed_time":3.432293474,"remaining_time":0.6586403448},
{"learn":[14.67783829],"iteration":839,"passed_time":3.43773101,"remaining_time":0.6548059066},
{"learn":[14.58811248],"iteration":840,"passed_time":3.441862579,"remaining_time":0.6507207493},
{"learn":[14.50025672],"iteration":841,"passed_time":3.443600931,"remaining_time":0.6461863979},
{"learn":[14.44031055],"iteration":842,"passed_time":3.447897281,"remaining_time":0.6421350809},
{"learn":[14.40900576],"iteration":843,"passed_time":3.450085365,"remaining_time":0.6376935035},
{"learn":[14.29037485],"iteration":844,"passed_time":3.455439841,"remaining_time":0.6338380773},
{"learn":[14.21514864],"iteration":845,"passed_time":3.461089496,"remaining_time":0.6300328398},
{"learn":[14.16577006],"iteration":846,"passed_time":3.464416778,"remaining_time":0.6258037392},
{"learn":[14.06240998],"iteration":847,"passed_time":3.468982108,"remaining_time":0.6217986798},
{"learn":[13.97255882],"iteration":848,"passed_time":3.471328527,"remaining_time":0.6173976533},
{"learn":[13.88443428],"iteration":849,"passed_time":3.48339422,"remaining_time":0.6147166271},
{"learn":[13.8229605],"iteration":850,"passed_time":3.485518621,"remaining_time":0.6102729431},
{"learn":[13.74039854],"iteration":851,"passed_time":3.488297826,"remaining_time":0.6059484486},
{"learn":[13.66911009],"iteration":852,"passed_time":3.489733977,"remaining_time":0.601396125},
{"learn":[13.58352866],"iteration":853,"passed_time":3.496794566,"remaining_time":0.5978126542},
{"learn":[13.49210653],"iteration":854,"passed_time":3.501084778,"remaining_time":0.5937512196},
{"learn":[13.37881513],"iteration":855,"passed_time":3.503634521,"remaining_time":0.5893964615},
{"learn":[13.31012374],"iteration":856,"passed_time":3.505740363,"remaining_time":0.5849718458},
{"learn":[13.2274003],"iteration":857,"passed_time":3.512045949,"remaining_time":0.5812476978},
{"learn":[13.16426725],"iteration":858,"passed_time":3.522958152,"remaining_time":0.5782736896},
{"learn":[13.1065713],"iteration":859,"passed_time":3.524535116,"remaining_time":0.5737615305},
{"learn":[13.03421372],"iteration":860,"passed_time":3.525965195,"remaining_time":0.5692324763},
{"learn":[12.95349453],"iteration":861,"passed_time":3.529514177,"remaining_time":0.5650498335},
{"learn":[12.89779191],"iteration":862,"passed_time":3.531689328,"remaining_time":0.5606505653},
{"learn":[12.84221299],"iteration":863,"passed_time":3.536747877,"remaining_time":0.556710314},
{"learn":[12.81425463],"iteration":864,"passed_time":3.53909395,"remaining_time":0.5523441424},
{"learn":[12.73540643],"iteration":865,"passed_time":3.541573937,"remaining_time":0.5480033574},
{"learn":[12.64875447],"iteration":866,"passed_time":3.543961405,"remaining_time":0.5436526723},
{"learn":[12.54334044],"iteration":867,"passed_time":3.55076259,"remaining_time":0.5399777211},
{"learn":[12.45097415],"iteration":868,"passed_time":3.558845031,"remaining_time":0.5364887215},
{"learn":[12.39843611],"iteration":869,"passed_time":3.560934668,"remaining_time":0.532093686},
{"learn":[12.32603939],"iteration":870,"passed_time":3.562374282,"remaining_time":0.527607672},
{"learn":[12.25531248],"iteration":871,"passed_time":3.563800033,"remaining_time":0.5231266104},
{"learn":[12.22844458],"iteration":872,"passed_time":3.577472145,"remaining_time":0.520434092},
{"learn":[12.1364738],"iteration":873,"passed_time":3.578999997,"remaining_time":0.5159656747},
{"learn":[12.06754436],"iteration":874,"passed_time":3.581158099,"remaining_time":0.5115940142},
{"learn":[12.04118835],"iteration":875,"passed_time":3.592285224,"remaining_time":0.5084969951},
{"learn":[11.97380766],"iteration":876,"passed_time":3.597417381,"remaining_time":0.5045408641},
{"learn":[11.8960559],"iteration":877,"passed_time":3.599078604,"remaining_time":0.5000997605},
{"learn":[11.82012017],"iteration":878,"passed_time":3.607590604,"remaining_time":0.4966080353},
{"learn":[11.75634838],"iteration":879,"passed_time":3.616110234,"remaining_time":0.493105941},
{"learn":[11.66436553],"iteration":880,"passed_time":3.622064266,"remaining_time":0.4892459111},
{"learn":[11.63884577],"iteration":881,"passed_time":3.640019919,"remaining_time":0.4869867919},
{"learn":[11.57128985],"iteration":882,"passed_time":3.643769129,"remaining_time":0.482809726},
{"learn":[11.4851394],"iteration":883,"passed_time":3.64706867,"remaining_time":0.4785746218},
{"learn":[11.43272741],"iteration":884,"passed_time":3.651632746,"remaining_time":0.47450595},
{"learn":[11.40801035],"iteration":885,"passed_time":3.656693169,"remaining_time":0.470500024},
{"learn":[11.32114327],"iteration":886,"passed_time":3.659254821,"remaining_time":0.4661733876},
{"learn":[11.23379148],"iteration":887,"passed_time":3.663879917,"remaining_time":0.4621109805},
{"learn":[11.19824972],"iteration":888,"passed_time":3.666006354,"remaining_time":0.4577353266},
{"learn":[11.1156692],"iteration":889,"passed_time":3.673199911,"remaining_time":0.4539910003},
{"learn":[11.07593153],"iteration":890,"passed_time":3.676072349,"remaining_time":0.4497103098},
{"learn":[11.0414299],"iteration":891,"passed_time":3.682469203,"remaining_time":0.4458594999},
{"learn":[10.95789375],"iteration":892,"passed_time":3.689985279,"remaining_time":0.4421370939},
{"learn":[10.87718401],"iteration":893,"passed_time":3.699595242,"remaining_time":0.4386544695},
{"learn":[10.81578294],"iteration":894,"passed_time":3.707224208,"remaining_time":0.434925745},
{"learn":[10.76758261],"iteration":895,"passed_time":3.709893977,"remaining_time":0.4306126937},
{"learn":[10.68699528],"iteration":896,"passed_time":3.714203813,"remaining_time":0.4264916307},
{"learn":[10.60513302],"iteration":897,"passed_time":3.722997524,"remaining_time":0.4228794515},
{"learn":[10.57768257],"iteration":898,"passed_time":3.725157268,"remaining_time":0.4185104383},
{"learn":[10.49997158],"iteration":899,"passed_time":3.727011653,"remaining_time":0.4141124058},
{"learn":[10.42683983],"iteration":900,"passed_time":3.728440376,"remaining_time":0.4096732488},
{"learn":[10.36962555],"iteration":901,"passed_time":3.735967981,"remaining_time":0.4059033948},
{"learn":[10.31372013],"iteration":902,"passed_time":3.743413841,"remaining_time":0.4021164369},
{"learn":[10.24945134],"iteration":903,"passed_time":3.745260106,"remaining_time":0.3977267369},
{"learn":[10.18610785],"iteration":904,"passed_time":3.746591979,"remaining_time":0.3932886608},
{"learn":[10.12367796],"iteration":905,"passed_time":3.760167959,"remaining_time":0.3901278015},
{"learn":[10.06375427],"iteration":906,"passed_time":3.763431792,"remaining_time":0.3858866116},
{"learn":[10.00255409],"iteration":907,"passed_time":3.765478355,"remaining_time":0.3815242386},
{"learn":[9.926665548],"iteration":908,"passed_time":3.76976899,"remaining_time":0.3773916151},
{"learn":[9.878975259],"iteration":909,"passed_time":3.774650821,"remaining_time":0.3733171142},
{"learn":[9.821429907],"iteration":910,"passed_time":3.777347222,"remaining_time":0.3690273356},
{"learn":[9.794991753],"iteration":911,"passed_time":3.781352859,"remaining_time":0.3648673812},
{"learn":[9.717199765],"iteration":912,"passed_time":3.782964178,"remaining_time":0.3604796095},
{"learn":[9.658388455],"iteration":913,"passed_time":3.78427074,"remaining_time":0.3560692381},
{"learn":[9.60227544],"iteration":914,"passed_time":3.787851479,"remaining_time":0.3518769133},
{"learn":[9.557266931],"iteration":915,"passed_time":3.790615262,"remaining_time":0.3476110065},
{"learn":[9.489594591],"iteration":916,"passed_time":3.794969223,"remaining_time":0.343492307},
{"learn":[9.452707425],"iteration":917,"passed_time":3.796990485,"remaining_time":0.3391647274},
{"learn":[9.387239288],"iteration":918,"passed_time":3.80191124,"remaining_time":0.3350977263},
{"learn":[9.332949655],"iteration":919,"passed_time":3.80528477,"remaining_time":0.3308943279},
{"learn":[9.297195074],"iteration":920,"passed_time":3.810867727,"remaining_time":0.326882248},
{"learn":[9.26218526],"iteration":921,"passed_time":3.815898338,"remaining_time":0.322820033},
{"learn":[9.199324116],"iteration":922,"passed_time":3.823423525,"remaining_time":0.318963826},
{"learn":[9.165283018],"iteration":923,"passed_time":3.835634995,"remaining_time":0.3154851295},
{"learn":[9.085280866],"iteration":924,"passed_time":3.838801708,"remaining_time":0.3112541925},
{"learn":[9.010865216],"iteration":925,"passed_time":3.843847725,"remaining_time":0.3071757361},
{"learn":[8.944718142],"iteration":926,"passed_time":3.857105024,"remaining_time":0.3037418195},
{"learn":[8.893071888],"iteration":927,"passed_time":3.860541932,"remaining_time":0.2995248051},
{"learn":[8.833702364],"iteration":928,"passed_time":3.870077121,"remaining_time":0.2957755388},
{"learn":[8.801622693],"iteration":929,"passed_time":3.87454895,"remaining_time":0.2916327166},
{"learn":[8.744203186],"iteration":930,"passed_time":3.881478107,"remaining_time":0.2876713097},
{"learn":[8.668646425],"iteration":931,"passed_time":3.884840039,"remaining_time":0.2834432647},
{"learn":[8.617666307],"iteration":932,"passed_time":3.889406602,"remaining_time":0.2793035823},
{"learn":[8.544065422],"iteration":933,"passed_time":3.891245691,"remaining_time":0.2749702522},
{"learn":[8.494906565],"iteration":934,"passed_time":3.893606452,"remaining_time":0.2706785234},
{"learn":[8.425272949],"iteration":935,"passed_time":3.896359911,"remaining_time":0.2664177717},
{"learn":[8.3548298],"iteration":936,"passed_time":3.898803694,"remaining_time":0.2621394159},
{"learn":[8.305953994],"iteration":937,"passed_time":3.904896035,"remaining_time":0.2581061345},
{"learn":[8.239190305],"iteration":938,"passed_time":3.909889008,"remaining_time":0.2539970495},
{"learn":[8.19222753],"iteration":939,"passed_time":3.915761246,"remaining_time":0.2499422072},
{"learn":[8.121659209],"iteration":940,"passed_time":3.917681542,"remaining_time":0.2456357183},
{"learn":[8.05823689],"iteration":941,"passed_time":3.931411972,"remaining_time":0.242061459},
{"learn":[8.025388323],"iteration":942,"passed_time":3.942372484,"remaining_time":0.2382982308},
{"learn":[7.981308364],"iteration":943,"passed_time":3.943885213,"remaining_time":0.2339592923},
{"learn":[7.937900657],"iteration":944,"passed_time":3.949115283,"remaining_time":0.2298426884},
{"learn":[7.886093317],"iteration":945,"passed_time":3.959300724,"remaining_time":0.2260065953},
{"learn":[7.841897705],"iteration":946,"passed_time":3.965284385,"remaining_time":0.2219219349},
{"learn":[7.773569633],"iteration":947,"passed_time":3.979851933,"remaining_time":0.2183041145},
{"learn":[7.708645906],"iteration":948,"passed_time":3.981656036,"remaining_time":0.2139773001},
{"learn":[7.65006971],"iteration":949,"passed_time":3.98353822,"remaining_time":0.2096599063},
{"learn":[7.595321654],"iteration":950,"passed_time":3.995826376,"remaining_time":0.2058837986},
{"learn":[7.554105357],"iteration":951,"passed_time":3.997438585,"remaining_time":0.2015515253},
{"learn":[7.505790539],"iteration":952,"passed_time":4.000159848,"remaining_time":0.1972796567},
{"learn":[7.443164808],"iteration":953,"passed_time":4.003222794,"remaining_time":0.1930275142},
{"learn":[7.390430918],"iteration":954,"passed_time":4.014613102,"remaining_time":0.1891702509},
{"learn":[7.344688264],"iteration":955,"passed_time":4.017667135,"remaining_time":0.1849135502},
{"learn":[7.282936229],"iteration":956,"passed_time":4.019899823,"remaining_time":0.1806224581},
{"learn":[7.243711497],"iteration":957,"passed_time":4.0219916,"remaining_time":0.1763294856},
{"learn":[7.183132516],"iteration":958,"passed_time":4.027424248,"remaining_time":0.1721839355},
{"learn":[7.123526117],"iteration":959,"passed_time":4.03295876,"remaining_time":0.1680399483},
{"learn":[7.064877266],"iteration":960,"passed_time":4.036517672,"remaining_time":0.163812892},
{"learn":[7.007171169],"iteration":961,"passed_time":4.038274687,"remaining_time":0.1595160479},
{"learn":[6.978473526],"iteration":962,"passed_time":4.042955904,"remaining_time":0.1553368312},
{"learn":[6.953654275],"iteration":963,"passed_time":4.046991137,"remaining_time":0.1511324491},
{"learn":[6.897136113],"iteration":964,"passed_time":4.052136811,"remaining_time":0.1469686926},
{"learn":[6.84152791],"iteration":965,"passed_time":4.053828361,"remaining_time":0.1426813295},
{"learn":[6.810243057],"iteration":966,"passed_time":4.060056514,"remaining_time":0.138554152},
{"learn":[6.765702031],"iteration":967,"passed_time":4.065300271,"remaining_time":0.1343900916},
{"learn":[6.723119399],"iteration":968,"passed_time":4.071856566,"remaining_time":0.1302657931},
{"learn":[6.679800946],"iteration":969,"passed_time":4.073675336,"remaining_time":0.1259899589},
{"learn":[6.652812578],"iteration":970,"passed_time":4.075998698,"remaining_time":0.1217342557},
{"learn":[6.606611395],"iteration":971,"passed_time":4.078339236,"remaining_time":0.1174830233},
{"learn":[6.553735161],"iteration":972,"passed_time":4.09138398,"remaining_time":0.1135327518},
{"learn":[6.501712118],"iteration":973,"passed_time":4.093004468,"remaining_time":0.1092588462},
{"learn":[6.47228931],"iteration":974,"passed_time":4.094489164,"remaining_time":0.1049869016},
{"learn":[6.421275073],"iteration":975,"passed_time":4.096066448,"remaining_time":0.1007229454},
{"learn":[6.399782489],"iteration":976,"passed_time":4.11078477,"remaining_time":0.09677384822},
{"learn":[6.34971072],"iteration":977,"passed_time":4.112521462,"remaining_time":0.09251070773},
{"learn":[6.30915522],"iteration":978,"passed_time":4.113978484,"remaining_time":0.08824672948},
{"learn":[6.260180651],"iteration":979,"passed_time":4.127730431,"remaining_time":0.08423939655},
{"learn":[6.211317625],"iteration":980,"passed_time":4.12956,"remaining_time":0.07998128439},
{"learn":[6.163152985],"iteration":981,"passed_time":4.131873529,"remaining_time":0.07573698933},
{"learn":[6.1157953],"iteration":982,"passed_time":4.140492161,"remaining_time":0.07160566301},
{"learn":[6.069679218],"iteration":983,"passed_time":4.147371325,"remaining_time":0.06743693211},
{"learn":[6.028163974],"iteration":984,"passed_time":4.148768674,"remaining_time":0.06317921839},
{"learn":[5.983563785],"iteration":985,"passed_time":4.150094403,"remaining_time":0.0589262897},
{"learn":[5.94299866],"iteration":986,"passed_time":4.151415468,"remaining_time":0.05467923108},
{"learn":[5.896185744],"iteration":987,"passed_time":4.160625571,"remaining_time":0.05053391381},
{"learn":[5.85043887],"iteration":988,"passed_time":4.166656557,"remaining_time":0.04634299507},
{"learn":[5.805431936],"iteration":989,"passed_time":4.169835216,"remaining_time":0.04211954764},
{"learn":[5.750739838],"iteration":990,"passed_time":4.17632902,"remaining_time":0.03792831602},
{"learn":[5.707031286],"iteration":991,"passed_time":4.186223762,"remaining_time":0.03375986905},
{"learn":[5.653932153],"iteration":992,"passed_time":4.187862588,"remaining_time":0.02952168994},
{"learn":[5.601837181],"iteration":993,"passed_time":4.195910351,"remaining_time":0.02532742667},
{"learn":[5.559940079],"iteration":994,"passed_time":4.204284197,"remaining_time":0.02112705627},
{"learn":[5.543834049],"iteration":995,"passed_time":4.206463481,"remaining_time":0.01689342764},
{"learn":[5.493386687],"iteration":996,"passed_time":4.208735505,"remaining_time":0.01266419911},
{"learn":[5.477764788],"iteration":997,"passed_time":4.222217698,"remaining_time":0.008461358112},
{"learn":[5.448247466],"iteration":998,"passed_time":4.226193826,"remaining_time":0.00423042425},
{"learn":[5.407923189],"iteration":999,"passed_time":4.228714883,"remaining_time":0}
]}